Workbook

Sheet START_HERE
A1: STAYOS — FINANCIAL MODEL SYSTEM v1
A3: Item | B3: Value
A4: Purpose | B4: Central financial-control workbook for StayOS. Supports COMMISSION or FIXED_FEE revenue, configurable by service, location, property/service type and customer segment.
A5: Core gate | B5: Protect the core marketplace objective: prove the accommodation loop and reach 10 real completed bookings before V1.1.
A6: Current stage | B6: Core engineering is built and locally validated. Immediate gate: authenticated real transaction smoke test, then deployment and marketplace activation.
A7: Mobile | B7: Native mobile is designed but not implemented. Current scope places native mobile after the Phase 2 gate; web/PWA is sufficient through the first 500 bookings.
A8: Existing conflict | B8: Current documents contain different revenue assumptions. This workbook keeps them configurable rather than silently resolving them.
A9: Use order | B9: DECISIONS → QUESTIONS → SERVICES → PRICING_MATRIX → ASSUMPTIONS → UNIT_ECONOMICS → MONTHLY_MODEL.
A10: Control rule | B10: Every monetized service must use COMMISSION or FIXED_FEE. Multiple pricing rules can coexist by location/type.

Sheet QUESTIONS
A1: FINANCIAL MODEL — DECISION QUESTIONS
A3: ID | B3: Category | C3: Question | D3: Why it matters | E3: Suggested A | F3: Suggested B | G3: Your Decision | H3: Status
A4: Q01 | B4: Core | C4: Primary monetization for accommodation in Closed Alpha? | D4: Sets first-transaction economics. | E4: Commission | F4: Fixed Fee | H4: OPEN
A5: Q02 | B5: Core | C5: Can each service choose its own monetization method? | D5: Required for service-level control. | E5: Yes | F5: No | H5: OPEN
A6: Q03 | B6: Accommodation | C6: Host commission in Alpha? | D6: Controls host acquisition. | E6: 0% first 3 bookings → 10% | F6: 0% first 50 hosts → ramp | H6: OPEN
A7: Q04 | B7: Accommodation | C7: Guest fee in Alpha? | D7: Controls booking friction. | E7: 0% first 10 bookings | F7: 0% first 100 bookings | H7: OPEN
A8: Q05 | B8: Accommodation | C8: Standard guest fee after Alpha? | D8: Core take rate. | E8: 4% | F8: 3–5% configurable | H8: OPEN
A9: Q06 | B9: Accommodation | C9: Cleaning fee ownership? | D9: Separates pass-through from revenue. | E9: 100% host | F9: Split/markup | H9: OPEN
A10: Q07 | B10: Pricing | C10: Should pricing vary by location? | D10: User explicitly requires it. | E10: Yes | F10: No | H10: OPEN
A11: Q08 | B11: Pricing | C11: Should pricing vary by property/service type? | D11: Different economics by segment. | E11: Yes | F11: No | H11: OPEN
A12: Q09 | B12: B2B | C12: Different agency rate for portfolio volume? | D12: Institutional supply may negotiate. | E12: Yes | F12: No | H12: OPEN
A13: Q10 | B13: Fixed Fee | C13: Fixed-fee basis? | D13: Defines unit of charge. | E13: Per transaction | F13: Per person/day/package | H13: OPEN
A14: Q11 | B14: Pricing | C14: Allow multiple pricing rules per service? | D14: Needed for location/type control. | E14: Yes | F14: No | H14: OPEN
A15: Q12 | B15: Pricing | C15: Minimum/maximum fee limits? | D15: Prevents extreme pricing. | E15: Yes | F15: No | H15: OPEN
... A29: Q26 | B29: B2B SaaS | C29: Include SaaS billing now? | D29: Current decision is proposed/deferred. | E29: No | F29: Pilot now | H29: OPEN

Sheet SERVICES
A1: STAYOS SERVICE REGISTER
A3: ID | B3: Service | C3: Category | D3: State | E3: Role | F3: Earliest Phase | G3: Revenue Options | H3: Suggested | I3: Your Model | J3: Location Sensitive | K3: Notes | L3: Evidence
A4: S01 | B4: Accommodation Booking | C4: Core | D4: LIVE | E4: CORE | F4: Closed Alpha | G4: COMMISSION / FIXED_FEE | H4: COMMISSION | J4: YES | K4: Primary marketplace revenue. | L4: MVP / DEC-010 / launch model
A5: S02 | B5: Cleaning Fee | C5: Pass-through | D5: LIVE | E5: CORE SUPPORT | F5: Closed Alpha | G5: PASS_THROUGH | H5: PASS_THROUGH | J5: YES | K5: Host-set fee; not automatically StayOS revenue. | L5: Execution plan
A6: S03 | B6: Car Rental | C6: Mobility | D6: PROPOSED / STUDY | E6: ADD-ON | F6: After 10 bookings | G6: COMMISSION / FIXED_FEE | H6: COMMISSION | J6: YES | K6: Manual test first; no build before core proof. | L6: User project discussion
A7: S04 | B7: Airport Transfer | C7: Mobility | D7: PROPOSED / STUDY | E7: ADD-ON | F7: After 10 bookings | G7: COMMISSION / FIXED_FEE | H7: COMMISSION | J7: YES | K7: Can be sold manually first. | L7: User project discussion
A8: S05 | B8: Trip Planning / Itinerary | C8: Travel Service | D8: PROPOSED / STUDY | E8: ADD-ON | F8: After 10 bookings | G8: FIXED_FEE / COMMISSION | H8: FIXED_FEE | J8: YES | K8: Manual service can validate willingness to pay. | L8: User project discussion
A9: S06 | B9: Tours / Experiences | C9: Travel Service | D9: PROPOSED / STUDY | E9: ADD-ON | F9: After core proof | G9: COMMISSION / FIXED_FEE | H9: COMMISSION | J9: YES | K9: Provider/legal validation required. | L9: User project discussion
A10: S07 | B10: Medical / Special Stay Support | C10: Specialized | D10: FUTURE STUDY | E10: ADD-ON | F10: Post-PMF | G10: COMMISSION / FIXED_FEE | H10: FIXED_FEE | J10: YES | K10: Only with demand/compliance evidence. | L10: Prior project discussions
A11: S08 | B11: B2B Property Management SaaS | C11: B2B | D11: DEFERRED / PROPOSED | E11: ADD-ON | F11: Phase 2/3 | G11: FIXED_FEE | H11: FIXED_FEE | J11: YES | K11: DEC-010 proposed; MVP defers SaaS billing. | L11: DEC-010 / MVP scope
A12: S09 | B12: Reciprocal Hosting Match | C12: Hospitality Exchange | D12: DISCOVERY ONLY | E12: SEPARATE | F12: After core + validation | G12: NONE initially | H12: NONE | J12: YES | K12: Strict simultaneous 1:1 reciprocal free hosting. | L12: Hospitality Exchange idea

Sheet PRICING_MATRIX
A1: SERVICE PRICING MATRIX — ADMIN CONTROL MODEL
A3: Rule | B3: Service ID | C3: Service | D3: Country | E3: City/Zone | F3: Property/Service Type | G3: Segment | H3: Method | I3: Rate % | J3: Fixed EGP | K3: Min EGP | L3: Max EGP | M3: Provider Payout % | N3: From | O3: To | P3: Active | Q3: Notes
A4: R001 | B4: S01 | C4: Accommodation Booking | D4: Egypt | E4: New Cairo | F4: Apartment | G4: All | H4: COMMISSION | I4: 10 | M4: 90 | P4: YES | Q4: Baseline example; confirm.
A5: R002 | B5: S01 | C5: Accommodation Booking | D5: Egypt | E5: New Cairo | F5: Luxury / Nile-view | G5: All | H5: COMMISSION | I5: 12 | M5: 88 | P5: YES | Q5: Illustrative location/type premium example.
A6: R003 | B6: S01 | C6: Accommodation Booking | D6: Egypt | E6: Maadi | F6: Apartment | G6: All | H6: COMMISSION | I6: 10 | M6: 90 | P6: YES | Q6: Illustrative example.
A7: R004 | B7: S01 | C7: Accommodation Booking | D7: Egypt | E7: Any | F7: Alpha host first 3 | G7: Host | H7: COMMISSION | I7: 0 | M7: 100 | P7: NO | Q7: Candidate alpha rule from GTM review.
A8: R005 | B8: S03 | C8: Car Rental | D8: Egypt | E8: New Cairo | F8: Economy | G8: Guest | H8: COMMISSION | I8: 12 | M8: 88 | P8: NO | Q8: Suggested test value only.
A9: R006 | B9: S04 | C9: Airport Transfer | D9: Egypt | E9: Cairo | F9: Sedan | G9: Guest | H9: FIXED_FEE | I9: 0 | J9: 250 | P9: NO | Q9: Suggested test value only.
A10: R007 | B10: S05 | C10: Trip Planning / Itinerary | D10: Egypt | E10: Any | F10: Custom | G10: Guest | H10: FIXED_FEE | I10: 0 | J10: 750 | P10: NO | Q10: Suggested test value only.
A11: R008 | B11: S06 | C11: Tours / Experiences | D11: Egypt | E11: Cairo | F11: Experience | G11: Guest | H11: COMMISSION | I11: 15 | M11: 85 | P11: NO | Q11: Suggested test value only.

Sheet ASSUMPTIONS
A1: OPERATING & FINANCIAL ASSUMPTIONS
A3: ID | B3: Metric | C3: Value | D3: Unit | E3: Scenario | F3: Override | G3: Source | H3: Notes
A4: A01 | B4: Average nightly rate | C4: 1500 | D4: EGP/night | E4: Base | G4: Launch model | H4: Estimate
A5: A02 | B5: Average booking length | C5: 3 | D5: nights | E5: Base | G5: Launch model | H5: Estimate
A6: A03 | B6: Average booking value | C6: =C4*C5 | D6: EGP/booking | E6: Base | G6: Calculated
A7: A04 | B7: Cleaning fee | C7: 300 | D7: EGP/booking | E7: Base | G7: Launch model | H7: Pass-through/retained decision required
A8: A05 | B8: Host commission | C8: 10 | D8: % | E8: Base | G8: Launch/GTM | H8: Configurable
A9: A06 | B9: Guest service fee | C9: 4 | D9: % | E9: Base | G9: GTM | H9: 0% may apply during Alpha
A10: A07 | B10: Payment processing | C10: 2.5 | D10: % | E10: Base | G10: User input | H10: Replace with actual contract
A11: A08 | B11: Payment fixed fee | C11: 10 | D11: EGP/booking | E11: Base | G11: User input | H11: Replace with actual contract
A12: A09 | B12: Host CAC | C12: 2000 | D12: EGP/host | E12: Base | G12: Launch model | H12: Range 1k–3k
A13: A10 | B13: Guest CAC | C13: 0 | D13: EGP/guest | E13: Alpha | G13: GTM | H13: Founder-led/organic
A14: A11 | B14: Ops cost / booking | C14: 300 | D14: EGP/booking | E14: Base | G14: Launch model | H14: Needs actual validation
A15: A12 | B15: Refund/chargeback loss | C15: 1 | D15: % GMV | E15: Base | G15: User input | H15: Validate after real bookings
A16: A13 | B16: Monthly fixed burn | C16: 420000 | D16: EGP/month | E16: Base | G16: Launch model | H16: Expected scenario
A17: A14 | B17: Monthly bookings | C17: 100 | D17: bookings | E17: Stage 1 | G17: Stage 1 target | H17: Adjust
A18: A15 | B18: Active listings | C18: 50 | D18: listings | E18: Alpha | G18: Scope freeze | H18: Target
A19: A16 | B19: Occupancy | C19: 50 | D19: % | E19: Stage 1 | G19: Launch model | H19: Unvalidated

Sheet UNIT_ECONOMICS
A1: UNIT ECONOMICS
A3: Metric | B3: Input / Formula | C3: Commission | D3: Fixed Fee | E3: Notes
A4: GMV / booking | B4: Assumptions!C6
A5: Host commission | B5: GMV × host rate | C5: =B4*ASSUMPTIONS!C9/100
A6: Guest service fee | B6: GMV × guest rate | C6: =B4*ASSUMPTIONS!C10/100
A7: Fixed service fee | D7: =0 | E7: Pull active rule per service when modeling a specific service
A8: Gross StayOS revenue | C8: =C5+C6 | D8: =D7
A9: Payment cost | C9: =B4*ASSUMPTIONS!C10/100+ASSUMPTIONS!C11 | D9: =B4*ASSUMPTIONS!C10/100+ASSUMPTIONS!C11 | E9: Temporary assumption
A10: Ops cost | B10: Assumptions!C14 | C10: =ASSUMPTIONS!C14 | D10: =ASSUMPTIONS!C14
A11: Refund loss | B11: GMV × loss % | C11: =B4*ASSUMPTIONS!C15/100 | D11: =B4*ASSUMPTIONS!C15/100
A12: Contribution margin | C12: =C8-C9-C10-C11 | D12: =D8-D9-D10-D11
A13: Take rate | C13: =IFERROR(C8/B4,0) | D13: =IFERROR(D8/B4,0)

Sheet MONTHLY_MODEL
A1: MONTHLY MARKETPLACE MODEL
A3: Month | B3: Listings | C3: Bookings | D3: ABV | E3: GMV | F3: Revenue | G3: Payment Cost | H3: Ops Cost | I3: Acq Cost | J3: Variable Cost | K3: Contribution | L3: Fixed Burn | M3: Net Cash
A4: M1 | B4: =ASSUMPTIONS!C18 | C4: =ASSUMPTIONS!C17 | D4: =ASSUMPTIONS!C6 | E4: =C4*D4 | F4: =E4*(ASSUMPTIONS!C9+ASSUMPTIONS!C10)/100 | G4: =E4*ASSUMPTIONS!C10/100+C4*ASSUMPTIONS!C11 | H4: =C4*ASSUMPTIONS!C14 | I4: 0 | J4: =G4+H4+I4 | K4: =F4-J4 | L4: =ASSUMPTIONS!C16 | M4: =K4-L4
A5: M2 | B5: =ASSUMPTIONS!C18 | C5: =ASSUMPTIONS!C17 | D5: =ASSUMPTIONS!C6 | E5: =C5*D5 | F5: =E5*(ASSUMPTIONS!C9+ASSUMPTIONS!C10)/100 | G5: =E5*ASSUMPTIONS!C10/100+C5*ASSUMPTIONS!C11 | H5: =C5*ASSUMPTIONS!C14 | I5: 0 | J5: =G5+H5+I5 | K5: =F5-J5 | L5: =ASSUMPTIONS!C16 | M5: =K5-L5
A6: M3 | B6: =ASSUMPTIONS!C18 | C6: =ASSUMPTIONS!C17 | D6: =ASSUMPTIONS!C6 | E6: =C6*D6 | F6: =E6*(ASSUMPTIONS!C9+ASSUMPTIONS!C10)/100 | G6: =E6*ASSUMPTIONS!C10/100+C6*ASSUMPTIONS!C11 | H6: =C6*ASSUMPTIONS!C14 | I6: 0 | J6: =G6+H6+I6 | K6: =F6-J6 | L6: =ASSUMPTIONS!C16 | M6: =K6-L6
A7: M4 | B7: =ASSUMPTIONS!C18 | C7: =ASSUMPTIONS!C17 | D7: =ASSUMPTIONS!C6 | E7: =C7*D7 | F7: =E7*(ASSUMPTIONS!C9+ASSUMPTIONS!C10)/100 | G7: =E7*ASSUMPTIONS!C10/100+C7*ASSUMPTIONS!C11 | H7: =C7*ASSUMPTIONS!C14 | I7: 0 | J7: =G7+H7+I7 | K7: =F7-J7 | L7: =ASSUMPTIONS!C16 | M7: =K7-L7
A8: M5 | B8: =ASSUMPTIONS!C18 | C8: =ASSUMPTIONS!C17 | D8: =ASSUMPTIONS!C6 | E8: =C8*D8 | F8: =E8*(ASSUMPTIONS!C9+ASSUMPTIONS!C10)/100 | G8: =E8*ASSUMPTIONS!C10/100+C8*ASSUMPTIONS!C11 | H8: =C8*ASSUMPTIONS!C14 | I8: 0 | J8: =G8+H8+I8 | K8: =F8-J8 | L8: =ASSUMPTIONS!C16 | M8: =K8-L8
A9: M6 | B9: =ASSUMPTIONS!C18 | C9: =ASSUMPTIONS!C17 | D9: =ASSUMPTIONS!C6 | E9: =C9*D9 | F9: =E9*(ASSUMPTIONS!C9+ASSUMPTIONS!C10)/100 | G9: =E9*ASSUMPTIONS!C10/100+C9*ASSUMPTIONS!C11 | H9: =C9*ASSUMPTIONS!C14 | I9: 0 | J9: =G9+H9+I9 | K9: =F9-J9 | L9: =ASSUMPTIONS!C16 | M9: =K9-L9
A10: M7 | B10: =ASSUMPTIONS!C18 | C10: =ASSUMPTIONS!C17 | D10: =ASSUMPTIONS!C6 | E10: =C10*D10 | F10: =E10*(ASSUMPTIONS!C9+ASSUMPTIONS!C10)/100 | G10: =E10*ASSUMPTIONS!C10/100+C10*ASSUMPTIONS!C11 | H10: =C10*ASSUMPTIONS!C14 | I10: 0 | J10: =G10+H10+I10 | K10: =F10-J10 | L10: =ASSUMPTIONS!C16 | M10: =K10-L10
A11: M8 | B11: =ASSUMPTIONS!C18 | C11: =ASSUMPTIONS!C17 | D11: =ASSUMPTIONS!C6 | E11: =C11*D11 | F11: =E11*(ASSUMPTIONS!C9+ASSUMPTIONS!C10)/100 | G11: =E11*ASSUMPTIONS!C10/100+C11*ASSUMPTIONS!C11 | H11: =C11*ASSUMPTIONS!C14 | I11: 0 | J11: =G11+H11+I11 | K11: =F11-J11 | L11: =ASSUMPTIONS!C16 | M11: =K11-L11
A12: M9 | B12: =ASSUMPTIONS!C18 | C12: =ASSUMPTIONS!C17 | D12: =ASSUMPTIONS!C6 | E12: =C12*D12 | F12: =E12*(ASSUMPTIONS!C9+ASSUMPTIONS!C10)/100 | G12: =E12*ASSUMPTIONS!C10/100+C12*ASSUMPTIONS!C11 | H12: =C12*ASSUMPTIONS!C14 | I12: 0 | J12: =G12+H12+I12 | K12: =F12-J12 | L12: =ASSUMPTIONS!C16 | M12: =K12-L12
A13: M10 | B13: =ASSUMPTIONS!C18 | C13: =ASSUMPTIONS!C17 | D13: =ASSUMPTIONS!C6 | E13: =C13*D13 | F13: =E13*(ASSUMPTIONS!C9+ASSUMPTIONS!C10)/100 | G13: =E13*ASSUMPTIONS!C10/100+C13*ASSUMPTIONS!C11 | H13: =C13*ASSUMPTIONS!C14 | I13: 0 | J13: =G13+H13+I13 | K13: =F13-J13 | L13: =ASSUMPTIONS!C16 | M13: =K13-L13
A14: M11 | B14: =ASSUMPTIONS!C18 | C14: =ASSUMPTIONS!C17 | D14: =ASSUMPTIONS!C6 | E14: =C14*D14 | F14: =E14*(ASSUMPTIONS!C9+ASSUMPTIONS!C10)/100 | G14: =E14*ASSUMPTIONS!C10/100+C14*ASSUMPTIONS!C11 | H14: =C14*ASSUMPTIONS!C14 | I14: 0 | J14: =G14+H14+I14 | K14: =F14-J14 | L14: =ASSUMPTIONS!C16 | M14: =K14-L14
A15: M12 | B15: =ASSUMPTIONS!C18 | C15: =ASSUMPTIONS!C17 | D15: =ASSUMPTIONS!C6 | E15: =C15*D15 | F15: =E15*(ASSUMPTIONS!C9+ASSUMPTIONS!C10)/100 | G15: =E15*ASSUMPTIONS!C10/100+C15*ASSUMPTIONS!C11 | H15: =C15*ASSUMPTIONS!C14 | I15: 0 | J15: =G15+H15+I15 | K15: =F15-J15 | L15: =ASSUMPTIONS!C16 | M15: =K15-L15

Sheet SCENARIOS
A1: SCENARIO COMPARISON
A3: Scenario | B3: Host % | C3: Guest % | D3: ABV | E3: Bookings/Mo | F3: Revenue/Mo | G3: Variable Cost | H3: Contribution | I3: Fixed Burn | J3: Net/Mo
A4: Alpha Candidate | B4: 0 | C4: 0 | D4: 4500 | E4: 10 | F4: =E4*D4*(B4+C4)/100 | G4: =E4*D4*ASSUMPTIONS!C10/100+E4*ASSUMPTIONS!C11 | H4: =F4-G4 | I4: =ASSUMPTIONS!C16 | J4: =H4-I4
A5: Base | B5: 10 | C5: 4 | D5: 4500 | E5: 100 | F5: =E5*D5*(B5+C5)/100 | G5: =E5*D5*ASSUMPTIONS!C10/100+E5*ASSUMPTIONS!C11 | H5: =F5-G5 | I5: =ASSUMPTIONS!C16 | J5: =H5-I5
A6: Conservative | B6: 8 | C6: 3 | D6: 4000 | E6: 75 | F6: =E6*D6*(B6+C6)/100 | G6: =E6*D6*ASSUMPTIONS!C10/100+E6*ASSUMPTIONS!C11 | H6: =F6-G6 | I6: =ASSUMPTIONS!C16 | J6: =H6-I6
A7: Growth | B7: 12 | C7: 5 | D7: 5000 | E7: 250 | F7: =E7*D7*(B7+C7)/100 | G7: =E7*D7*ASSUMPTIONS!C10/100+E7*ASSUMPTIONS!C11 | H7: =F7-G7 | I7: =ASSUMPTIONS!C16 | J7: =H7-I7

Sheet SERVICE_ROADMAP
A1: SERVICE ROADMAP — PROTECT THE CORE
A3: Item | B3: Type | C3: State | D3: Earliest Start | E3: Gate | F3: Why Not Now | G3: Monetization | H3: Engineering | I3: Priority | J3: Decision
A4: Accommodation marketplace | B4: Core | C4: LIVE / VALIDATION | D4: NOW | E4: Authenticated smoke + deployment | F4: This is the project goal. | G4: Commission / Fixed | H4: Built | I4: P0 | J4: EXECUTE
A5: Car rental | B5: Add-on | C5: Study | D5: After 10 bookings | E5: Core proof | F5: Would distract from liquidity. | G5: Commission / Fixed | H5: Later | I5: P2 | J5: MANUAL STUDY
A6: Airport transfer | B6: Add-on | C6: Study | D6: After 10 bookings | E6: Core proof | F6: Can test manually first. | G6: Commission / Fixed | H6: Later | I6: P2 | J6: MANUAL STUDY
A7: Trip planning | B7: Add-on | C7: Study | D7: After 10 bookings | E7: Demand signal | F7: Can sell manually first. | G7: Fixed Fee | H7: Optional | I7: P2 | J7: MANUAL TEST
A8: Tours / experiences | B8: Add-on | C8: Study | D8: After core proof | E8: Provider/legal validation | F8: Adds operational complexity. | G8: Commission / Fixed | H8: Later | I8: P2 | J8: DEFER
A9: Medical / special stay | B9: Add-on | C9: Future | D9: Post-PMF | E9: Demand + compliance | F9: Not launch-critical. | G9: Commission / Fixed | H9: Yes | I9: P3 | J9: DEFER
A10: B2B SaaS | B10: Future | C10: Deferred/Proposed | D10: Phase 2/3 | E10: PMF + B2B scale | F10: DEC-010 proposed; MVP defers billing. | G10: Fixed Fee | H10: Yes | I10: P3 | J10: DEFER
A11: Reciprocal Hosting Match | B11: Separate experiment | C11: Discovery | D11: After 10 bookings + validation | E11: Liquidity/legal/competitive study | F11: Different marketplace problem. | G11: None initially | H11: Yes | I11: P3 | J11: DISCOVERY ONLY
A12: Native mobile | B12: Platform | C12: Designed, not built | D12: After 500 bookings / Phase 2 | E12: 500 listings + 200 bookings/mo + positive unit economics | F12: Web/PWA sufficient before gate. | G12: N/A | H12: Yes | I12: P3 | J12: DEFER

Sheet DECISIONS
A1: EXECUTIVE COMMERCIAL DECISIONS
A3: ID | B3: Decision | C3: Evidence | D3: Recommended Position | E3: Your Decision | F3: Date | G3: Owner | H3: Status
A4: D01 | B4: Alpha host commission | C4: GTM review: 0% first 3, then 10%. | D4: 0% first 3 per host → 10% standard | G4: Founder | H4: OPEN
A5: D02 | B5: Alpha guest fee | C5: GTM review: 0% during alpha/first 10. | D5: 0% first 10 → 4% standard | G5: Founder | H5: OPEN
A6: D03 | B6: Cleaning fee | C6: Existing execution plan: host-set pass-through. | D6: 100% host | G6: Founder | H6: OPEN
A7: D04 | B7: Location pricing | C7: User requires it. | D7: Enable country/city/zone pricing | G7: Founder | H7: OPEN
A8: D05 | B8: Type pricing | C8: User requires it. | D8: Enable property/service type dimension | G8: Founder | H8: OPEN
A9: D06 | B9: Agency pricing | C9: Institutional partners may negotiate. | D9: Allow portfolio-based rules | G9: Founder | H9: OPEN
A10: D07 | B10: Two monetization methods | C10: User requires commission OR fixed fee. | D10: Support both at service/rule level | G10: Founder | H10: OPEN
A11: D08 | B11: Native mobile | C11: MVP scope defers until 500 bookings. | D11: Do not build now | G11: Founder | H11: OPEN
A12: D09 | B12: Paid add-ons | C12: Need to protect core. | D12: Manual test after 10 bookings; build only on evidence | G12: Founder | H12: OPEN
A13: D10 | B13: Reciprocal Hosting | C13: Discovery only today. | D13: Separate validation after core proof | G13: Founder | H13: OPEN

Sheet SOURCE_NOTES
A1: SOURCE / STATUS NOTES
A3: Topic | B3: Source | C3: Supports | D3: Status | E3: Limitation
A4: MVP gate | B4: MVP_SCOPE_FREEZE.md | C4: 10 completed bookings, EGP payment, host payout, 0 P0 safety/fraud | D4: Authoritative | E4: Not a pricing decision.
A5: Revenue | B5: DECISION_LOG DEC-010 | C5: 8–12% host + 3–5% guest + B2B SaaS proposed | D5: PROPOSED | E5: Requires validation.
A6: Launch model | B6: LAUNCH_FINANCIAL_MODEL.md | C6: 10% host, 3–5% guest, 13–17% take rate, ABV 4,500 | D6: Model | E6: Contains estimates.
A7: GTM | B7: 05_GO_TO_MARKET_VALIDATION.md | C7: 0% host first 3; 0% guest first 10; standard 10% + 4% | D7: Recommendation | E7: Needs founder approval.
A8: Mobile | B8: MVP_SCOPE_FREEZE / 08_MOBILE_MAP | C8: Native app deferred; web/PWA sufficient through first 500 bookings; no mobile code | D8: Current scope | E8: Design exists, implementation does not.
A9: Core loop | B9: 05_CLOSED_ALPHA_PLAYBOOK / CLOSED_ALPHA_EXECUTION_PLAN | C9: Supply → demand → booking → trust → repeat; 10 bookings exit gate | D9: Current direction | E9: Older docs conflict on 4 vs 6 weeks.
A10: Reciprocal Hosting | B10: Hospitality Exchange idea.md | C10: Strict 1:1 simultaneous reciprocal free hosting | D10: Discovery | E10: Not current core.
