Workbook

Sheet 01_CONTROL_PANEL
A1: StayOS Financial Model v2 — Control Panel
A3: Model status | B3: DRAFT — decision-support model, not yet validated | D3: How to use
A4: Model date | B4: 46256 | D4: Edit assumptions in 02_MARKETPLACE_ASSUMPTIONS only.
A5: Current evidence baseline | B5: Assessment Evidence Freeze v1 — 2026-08-22 | D5: Current facts and planning assumptions are explicitly separated.
A6: Current commercial reality | B6: 0 real users / 0 real listings / 0 bookings / EGP 0 revenue | D6: Alpha uses 0% platform commission by current executive decision.
A7: Alpha stage | B7: FINISH V1 → VALIDATE | D7: Post-Alpha commission is a scenario assumption, not a validated fact.
A8: Alpha platform commission | B8: 0 | D8: The model separates supply, demand, transactions, monetization and costs.
A9: Post-Alpha Base Commission | B9: 0.1 | D9: No number marked 'Draft assumption' should be treated as evidence.
A10: Post-Alpha Upside Commission | B10: 0.12
A11: Post-Alpha Downside Commission | B11: 0.08
A12: Alpha booking gate | B12: 7
A13: Original workbook Studio ADR | B13: 1800
A14: Original workbook Apartment ADR | B14: 2500
A15: Original workbook Villa ADR | B15: 6000
A19: Important model discipline
A20: Current evidence is separated from assumptions.
A21: The original workbook's ADRs are retained as editable draft assumptions.
A22: Alpha commission is 0% per current executive direction; post-alpha rates are scenarios.
A23: Seed listings are not counted as real commercial supply.
A24: Do not use modeled CAC/LTV/breakeven as validated evidence before real transactions.
A25: The model is intentionally built to be revised after Alpha evidence arrives.

Sheet 02_MARKETPLACE_ASSUMPTIONS
A1: Marketplace Assumptions — Source / Status Controlled
A3: Variable | B3: Value | C3: Unit | D3: Scenario | E3: Status | F3: Source / rationale | G3: Validation required | H3: Notes
A4: Studio ADR | B4: 1800 | C4: EGP/night | D4: Base | E4: Draft assumption | F4: Carried from founder-provided Excel | G4: Yes | H4: Replace with observed listing prices
A5: Apartment ADR | B5: 2500 | C5: EGP/night | D5: Base | E5: Draft assumption | F5: Carried from founder-provided Excel | G5: Yes | H5: Replace with observed listing prices
A6: Villa ADR | B6: 6000 | C6: EGP/night | D6: Base | E6: Draft assumption | F6: Carried from founder-provided Excel | G6: Yes | H6: Replace with observed listing prices
A7: Studio mix | B7: 0.5 | C7: % listings | D7: Base | E7: Draft assumption | F7: Model placeholder | G7: Yes | H7: Must reconcile to acquired supply
A8: Apartment mix | B8: 0.4 | C8: % listings | D8: Base | E8: Draft assumption | F8: Model placeholder | G8: Yes | H8: Must reconcile to acquired supply
A9: Villa mix | B9: 0.1 | C9: % listings | D9: Base | E9: Draft assumption | F9: Model placeholder | G9: Yes | H9: Must reconcile to acquired supply
A10: Average nights / booking | B10: 2.5 | C10: nights | D10: Base | E10: Draft assumption | F10: Model placeholder | G10: Yes | H10: Not present in source workbook
A11: Booking conversion | B11: 0.03 | C11: % search/qualified demand | D11: Base | E11: Draft assumption | F11: Model placeholder | G11: Yes | H11: Replace with alpha evidence
A12: Monthly qualified demand | B12: 100 | C12: qualified users | D12: Base | E12: Draft assumption | F12: Model placeholder | G12: Yes | H12: Replace with measured funnel
A13: Cancellation rate | B13: 0.05 | C13: % bookings | D13: Base | E13: Draft assumption | F13: Yes | G13: Yes | H13: Replace with actual
A14: Refund / service credit rate | B14: 0.02 | C14: % GMV | D14: Base | E14: Draft assumption | F14: Model placeholder | G14: Yes | H14: Replace with actual
A15: Payment processing rate | B15: 0.03 | C15: % GMV | D15: Base | E15: Draft assumption | F15: Model placeholder | G15: Yes | H15: Processor dependent
... A25: Monthly office/admin | B25: 5000 | C25: EGP/month | D25: Base | E25: Draft assumption | F25: Planning placeholder | G25: Yes | H25: Replace with actual

Sheet 03_SUPPLY_MODEL
A1: Supply Model — Bookable Inventory Ramp
A3: Month | B3: Real bookable listings | C3: Studio % | D3: Apartment % | E3: Villa % | F3: Studios | G3: Apartments | H3: Villas | I3: Available nights | J3: Notes
A4: 1 | B4: 0 | C4: =02_MARKETPLACE_ASSUMPTIONS!$B$7 | D4: =02_MARKETPLACE_ASSUMPTIONS!$B$8 | E4: =02_MARKETPLACE_ASSUMPTIONS!$B$9 | F4: =B4*C4 | G4: =B4*D4 | H4: =B4*E4 | I4: =B4*30 | J4: Illustrative ramp — replace with actual acquired listings
A5: 2 | B5: 0 | C5: =02_MARKETPLACE_ASSUMPTIONS!$B$7 | D5: =02_MARKETPLACE_ASSUMPTIONS!$B$8 | E5: =02_MARKETPLACE_ASSUMPTIONS!$B$9 | F5: =B5*C5 | G5: =B5*D5 | H5: =B5*E5 | I5: =B5*30 | J5: Illustrative ramp — replace with actual acquired listings
A6: 3 | B6: 3 | C6: =02_MARKETPLACE_ASSUMPTIONS!$B$7 | D6: =02_MARKETPLACE_ASSUMPTIONS!$B$8 | E6: =02_MARKETPLACE_ASSUMPTIONS!$B$9 | F6: =B6*C6 | G6: =B6*D6 | H6: =B6*E6 | I6: =B6*30 | J6: Illustrative ramp — replace with actual acquired listings
A7: 4 | B7: 3 | C7: =02_MARKETPLACE_ASSUMPTIONS!$B$7 | D7: =02_MARKETPLACE_ASSUMPTIONS!$B$8 | E7: =02_MARKETPLACE_ASSUMPTIONS!$B$9 | F7: =B7*C7 | G7: =B7*D7 | H7: =B7*E7 | I7: =B7*30 | J7: Illustrative ramp — replace with actual acquired listings
A8: 5 | B8: 5 | C8: =02_MARKETPLACE_ASSUMPTIONS!$B$7 | D8: =02_MARKETPLACE_ASSUMPTIONS!$B$8 | E8: =02_MARKETPLACE_ASSUMPTIONS!$B$9 | F8: =B8*C8 | G8: =B8*D8 | H8: =B8*E8 | I8: =B8*30 | J8: Illustrative ramp — replace with actual acquired listings
A9: 6 | B9: 5 | C9: =02_MARKETPLACE_ASSUMPTIONS!$B$7 | D9: =02_MARKETPLACE_ASSUMPTIONS!$B$8 | E9: =02_MARKETPLACE_ASSUMPTIONS!$B$9 | F9: =B9*C9 | G9: =B9*D9 | H9: =B9*E9 | I9: =B9*30 | J9: Illustrative ramp — replace with actual acquired listings
A10: 7 | B10: 7 | C10: =02_MARKETPLACE_ASSUMPTIONS!$B$7 | D10: =02_MARKETPLACE_ASSUMPTIONS!$B$8 | E10: =02_MARKETPLACE_ASSUMPTIONS!$B$9 | F10: =B10*C10 | G10: =B10*D10 | H10: =B10*E10 | I10: =B10*30 | J10: Illustrative ramp — replace with actual acquired listings
A11: 8 | B11: 7 | C11: =02_MARKETPLACE_ASSUMPTIONS!$B$7 | D11: =02_MARKETPLACE_ASSUMPTIONS!$B$8 | E11: =02_MARKETPLACE_ASSUMPTIONS!$B$9 | F11: =B11*C11 | G11: =B11*D11 | H11: =B11*E11 | I11: =B11*30 | J11: Illustrative ramp — replace with actual acquired listings
A12: 9 | B12: 10 | C12: =02_MARKETPLACE_ASSUMPTIONS!$B$7 | D12: =02_MARKETPLACE_ASSUMPTIONS!$B$8 | E12: =02_MARKETPLACE_ASSUMPTIONS!$B$9 | F12: =B12*C12 | G12: =B12*D12 | H12: =B12*E12 | I12: =B12*30 | J12: Illustrative ramp — replace with actual acquired listings
A13: 10 | B13: 10 | C13: =02_MARKETPLACE_ASSUMPTIONS!$B$7 | D13: =02_MARKETPLACE_ASSUMPTIONS!$B$8 | E13: =02_MARKETPLACE_ASSUMPTIONS!$B$9 | F13: =B13*C13 | G13: =B13*D13 | H13: =B13*E13 | I13: =B13*30 | J13: Illustrative ramp — replace with actual acquired listings
A14: 11 | B14: 12 | C14: =02_MARKETPLACE_ASSUMPTIONS!$B$7 | D14: =02_MARKETPLACE_ASSUMPTIONS!$B$8 | E14: =02_MARKETPLACE_ASSUMPTIONS!$B$9 | F14: =B14*C14 | G14: =B14*D14 | H14: =B14*E14 | I14: =B14*30 | J14: Illustrative ramp — replace with actual acquired listings
A15: 12 | B15: 12 | C15: =02_MARKETPLACE_ASSUMPTIONS!$B$7 | D15: =02_MARKETPLACE_ASSUMPTIONS!$B$8 | E15: =02_MARKETPLACE_ASSUMPTIONS!$B$9 | F15: =B15*C15 | G15: =B15*D15 | H15: =B15*E15 | I15: =B15*30 | J15: Illustrative ramp — replace with actual acquired listings
... A27: 24 | B27: 40 | C27: =02_MARKETPLACE_ASSUMPTIONS!$B$7 | D27: =02_MARKETPLACE_ASSUMPTIONS!$B$8 | E27: =02_MARKETPLACE_ASSUMPTIONS!$B$9 | F27: =B27*C27 | G27: =B27*D27 | H27: =B27*E27 | I27: =B27*30 | J27: Illustrative ramp — replace with actual acquired listings

Sheet 04_DEMAND_MODEL
A1: Demand Funnel — From Qualified Demand to Bookings
A3: Month | B3: Qualified demand | C3: Conversion | D3: Gross booking intents | E3: Cancellation rate | F3: Completed bookings | G3: Avg nights/booking | H3: Booked nights | I3: Avg ADR | J3: GMV | K3: Status
A4: 1 | B4: =02_MARKETPLACE_ASSUMPTIONS!$B$12*(1+0.05)^0 | C4: =02_MARKETPLACE_ASSUMPTIONS!$B$11 | D4: =B4*C4 | E4: =02_MARKETPLACE_ASSUMPTIONS!$B$13 | F4: =D4*(1-E4) | G4: =02_MARKETPLACE_ASSUMPTIONS!$B$10 | H4: =F4*G4 | I4: =(02_MARKETPLACE_ASSUMPTIONS!$B$4*02_MARKETPLACE_ASSUMPTIONS!$B$7+02_MARKETPLACE_ASSUMPTIONS!$B$5*02_MARKETPLACE_ASSUMPTIONS!$B$8+02_MARKETPLACE_ASSUMPTIONS!$B$6*02_MARKETPLACE_ASSUMPTIONS!$B$9) | J4: =H4*I4 | K4: Illustrative — validate in Alpha
A5: 2 | B5: =02_MARKETPLACE_ASSUMPTIONS!$B$12*(1+0.05)^1 | C5: =02_MARKETPLACE_ASSUMPTIONS!$B$11 | D5: =B5*C5 | E5: =02_MARKETPLACE_ASSUMPTIONS!$B$13 | F5: =D5*(1-E5) | G5: =02_MARKETPLACE_ASSUMPTIONS!$B$10 | H5: =F5*G5 | I5: =(02_MARKETPLACE_ASSUMPTIONS!$B$4*02_MARKETPLACE_ASSUMPTIONS!$B$7+02_MARKETPLACE_ASSUMPTIONS!$B$5*02_MARKETPLACE_ASSUMPTIONS!$B$8+02_MARKETPLACE_ASSUMPTIONS!$B$6*02_MARKETPLACE_ASSUMPTIONS!$B$9) | J5: =H5*I5 | K5: Illustrative — validate in Alpha
A6: 3 | B6: =02_MARKETPLACE_ASSUMPTIONS!$B$12*(1+0.05)^2 | C6: =02_MARKETPLACE_ASSUMPTIONS!$B$11 | D6: =B6*C6 | E6: =02_MARKETPLACE_ASSUMPTIONS!$B$13 | F6: =D6*(1-E6) | G6: =02_MARKETPLACE_ASSUMPTIONS!$B$10 | H6: =F6*G6 | I6: =(02_MARKETPLACE_ASSUMPTIONS!$B$4*02_MARKETPLACE_ASSUMPTIONS!$B$7+02_MARKETPLACE_ASSUMPTIONS!$B$5*02_MARKETPLACE_ASSUMPTIONS!$B$8+02_MARKETPLACE_ASSUMPTIONS!$B$6*02_MARKETPLACE_ASSUMPTIONS!$B$9) | J6: =H6*I6 | K6: Illustrative — validate in Alpha
A7: 4 | B7: =02_MARKETPLACE_ASSUMPTIONS!$B$12*(1+0.05)^3 | C7: =02_MARKETPLACE_ASSUMPTIONS!$B$11 | D7: =B7*C7 | E7: =02_MARKETPLACE_ASSUMPTIONS!$B$13 | F7: =D7*(1-E7) | G7: =02_MARKETPLACE_ASSUMPTIONS!$B$10 | H7: =F7*G7 | I7: =(02_MARKETPLACE_ASSUMPTIONS!$B$4*02_MARKETPLACE_ASSUMPTIONS!$B$7+02_MARKETPLACE_ASSUMPTIONS!$B$5*02_MARKETPLACE_ASSUMPTIONS!$B$8+02_MARKETPLACE_ASSUMPTIONS!$B$6*02_MARKETPLACE_ASSUMPTIONS!$B$9) | J7: =H7*I7 | K7: Illustrative — validate in Alpha
A8: 5 | B8: =02_MARKETPLACE_ASSUMPTIONS!$B$12*(1+0.05)^4 | C8: =02_MARKETPLACE_ASSUMPTIONS!$B$11 | D8: =B8*C8 | E8: =02_MARKETPLACE_ASSUMPTIONS!$B$13 | F8: =D8*(1-E8) | G8: =02_MARKETPLACE_ASSUMPTIONS!$B$10 | H8: =F8*G8 | I8: =(02_MARKETPLACE_ASSUMPTIONS!$B$4*02_MARKETPLACE_ASSUMPTIONS!$B$7+02_MARKETPLACE_ASSUMPTIONS!$B$5*02_MARKETPLACE_ASSUMPTIONS!$B$8+02_MARKETPLACE_ASSUMPTIONS!$B$6*02_MARKETPLACE_ASSUMPTIONS!$B$9) | J8: =H8*I8 | K8: Illustrative — validate in Alpha
A9: 6 | B9: =02_MARKETPLACE_ASSUMPTIONS!$B$12*(1+0.05)^5 | C9: =02_MARKETPLACE_ASSUMPTIONS!$B$11 | D9: =B9*C9 | E9: =02_MARKETPLACE_ASSUMPTIONS!$B$13 | F9: =D9*(1-E9) | G9: =02_MARKETPLACE_ASSUMPTIONS!$B$10 | H9: =F9*G9 | I9: =(02_MARKETPLACE_ASSUMPTIONS!$B$4*02_MARKETPLACE_ASSUMPTIONS!$B$7+02_MARKETPLACE_ASSUMPTIONS!$B$5*02_MARKETPLACE_ASSUMPTIONS!$B$8+02_MARKETPLACE_ASSUMPTIONS!$B$6*02_MARKETPLACE_ASSUMPTIONS!$B$9) | J9: =H9*I9 | K9: Illustrative — validate in Alpha
A10: 7 | B10: =02_MARKETPLACE_ASSUMPTIONS!$B$12*(1+0.05)^6 | C10: =02_MARKETPLACE_ASSUMPTIONS!$B$11 | D10: =B10*C10 | E10: =02_MARKETPLACE_ASSUMPTIONS!$B$13 | F10: =D10*(1-E10) | G10: =02_MARKETPLACE_ASSUMPTIONS!$B$10 | H10: =F10*G10 | I10: =(02_MARKETPLACE_ASSUMPTIONS!$B$4*02_MARKETPLACE_ASSUMPTIONS!$B$7+02_MARKETPLACE_ASSUMPTIONS!$B$5*02_MARKETPLACE_ASSUMPTIONS!$B$8+02_MARKETPLACE_ASSUMPTIONS!$B$6*02_MARKETPLACE_ASSUMPTIONS!$B$9) | J10: =H10*I10 | K10: Illustrative — validate in Alpha
A11: 8 | B11: =02_MARKETPLACE_ASSUMPTIONS!$B$12*(1+0.05)^7 | C11: =02_MARKETPLACE_ASSUMPTIONS!$B$11 | D11: =B11*C11 | E11: =02_MARKETPLACE_ASSUMPTIONS!$B$13 | F11: =D11*(1-E11) | G11: =02_MARKETPLACE_ASSUMPTIONS!$B$10 | H11: =F11*G11 | I11: =(02_MARKETPLACE_ASSUMPTIONS!$B$4*02_MARKETPLACE_ASSUMPTIONS!$B$7+02_MARKETPLACE_ASSUMPTIONS!$B$5*02_MARKETPLACE_ASSUMPTIONS!$B$8+02_MARKETPLACE_ASSUMPTIONS!$B$6*02_MARKETPLACE_ASSUMPTIONS!$B$9) | J11: =H11*I11 | K11: Illustrative — validate in Alpha
A12: 9 | B12: =02_MARKETPLACE_ASSUMPTIONS!$B$12*(1+0.05)^8 | C12: =02_MARKETPLACE_ASSUMPTIONS!$B$11 | D12: =B12*C12 | E12: =02_MARKETPLACE_ASSUMPTIONS!$B$13 | F12: =D12*(1-E12) | G12: =02_MARKETPLACE_ASSUMPTIONS!$B$10 | H12: =F12*G12 | I12: =(02_MARKETPLACE_ASSUMPTIONS!$B$4*02_MARKETPLACE_ASSUMPTIONS!$B$7+02_MARKETPLACE_ASSUMPTIONS!$B$5*02_MARKETPLACE_ASSUMPTIONS!$B$8+02_MARKETPLACE_ASSUMPTIONS!$B$6*02_MARKETPLACE_ASSUMPTIONS!$B$9) | J12: =H12*I12 | K12: Illustrative — validate in Alpha
A13: 10 | B13: =02_MARKETPLACE_ASSUMPTIONS!$B$12*(1+0.05)^9 | C13: =02_MARKETPLACE_ASSUMPTIONS!$B$11 | D13: =B13*C13 | E13: =02_MARKETPLACE_ASSUMPTIONS!$B$13 | F13: =D13*(1-E13) | G13: =02_MARKETPLACE_ASSUMPTIONS!$B$10 | H13: =F13*G13 | I13: =(02_MARKETPLACE_ASSUMPTIONS!$B$4*02_MARKETPLACE_ASSUMPTIONS!$B$7+02_MARKETPLACE_ASSUMPTIONS!$B$5*02_MARKETPLACE_ASSUMPTIONS!$B$8+02_MARKETPLACE_ASSUMPTIONS!$B$6*02_MARKETPLACE_ASSUMPTIONS!$B$9) | J13: =H13*I13 | K13: Illustrative — validate in Alpha
A14: 11 | B14: =02_MARKETPLACE_ASSUMPTIONS!$B$12*(1+0.05)^10 | C14: =02_MARKETPLACE_ASSUMPTIONS!$B$11 | D14: =B14*C14 | E14: =02_MARKETPLACE_ASSUMPTIONS!$B$13 | F14: =D14*(1-E14) | G14: =02_MARKETPLACE_ASSUMPTIONS!$B$10 | H14: =F14*G14 | I14: =(02_MARKETPLACE_ASSUMPTIONS!$B$4*02_MARKETPLACE_ASSUMPTIONS!$B$7+02_MARKETPLACE_ASSUMPTIONS!$B$5*02_MARKETPLACE_ASSUMPTIONS!$B$8+02_MARKETPLACE_ASSUMPTIONS!$B$6*02_MARKETPLACE_ASSUMPTIONS!$B$9) | J14: =H14*I14 | K14: Illustrative — validate in Alpha
A15: 12 | B15: =02_MARKETPLACE_ASSUMPTIONS!$B$12*(1+0.05)^11 | C15: =02_MARKETPLACE_ASSUMPTIONS!$B$11 | D15: =B15*C15 | E15: =02_MARKETPLACE_ASSUMPTIONS!$B$13 | F15: =D15*(1-E15) | G15: =02_MARKETPLACE_ASSUMPTIONS!$B$10 | H15: =F15*G15 | I15: =(02_MARKETPLACE_ASSUMPTIONS!$B$4*02_MARKETPLACE_ASSUMPTIONS!$B$7+02_MARKETPLACE_ASSUMPTIONS!$B$5*02_MARKETPLACE_ASSUMPTIONS!$B$8+02_MARKETPLACE_ASSUMPTIONS!$B$6*02_MARKETPLACE_ASSUMPTIONS!$B$9) | J15: =H15*I15 | K15: Illustrative — validate in Alpha
A16: 13 | B16: =02_MARKETPLACE_ASSUMPTIONS!$B$12*(1+0.05)^12 | C16: =02_MARKETPLACE_ASSUMPTIONS!$B$11 | D16: =B16*C16 | E16: =02_MARKETPLACE_ASSUMPTIONS!$B$13 | F16: =D16*(1-E16) | G16: =02_MARKETPLACE_ASSUMPTIONS!$B$10 | H16: =F16*G16 | I16: =(02_MARKETPLACE_ASSUMPTIONS!$B$4*02_MARKETPLACE_ASSUMPTIONS!$B$7+02_MARKETPLACE_ASSUMPTIONS!$B$5*02_MARKETPLACE_ASSUMPTIONS!$B$8+02_MARKETPLACE_ASSUMPTIONS!$B$6*02_MARKETPLACE_ASSUMPTIONS!$B$9) | J16: =H16*I16 | K16: Illustrative — validate in Alpha
A17: 14 | B17: =02_MARKETPLACE_ASSUMPTIONS!$B$12*(1+0.05)^13 | C17: =02_MARKETPLACE_ASSUMPTIONS!$B$11 | D17: =B17*C17 | E17: =02_MARKETPLACE_ASSUMPTIONS!$B$13 | F17: =D17*(1-E17) | G17: =02_MARKETPLACE_ASSUMPTIONS!$B$10 | H17: =F17*G17 | I17: =(02_MARKETPLACE_ASSUMPTIONS!$B$4*02_MARKETPLACE_ASSUMPTIONS!$B$7+02_MARKETPLACE_ASSUMPTIONS!$B$5*02_MARKETPLACE_ASSUMPTIONS!$B$8+02_MARKETPLACE_ASSUMPTIONS!$B$6*02_MARKETPLACE_ASSUMPTIONS!$B$9) | J17: =H17*I17 | K17: Illustrative — validate in Alpha
A18: 15 | B18: =02_MARKETPLACE_ASSUMPTIONS!$B$12*(1+0.05)^14 | C18: =02_MARKETPLACE_ASSUMPTIONS!$B$11 | D18: =B18*C18 | E18: =02_MARKETPLACE_ASSUMPTIONS!$B$13 | F18: =D18*(1-E18) | G18: =02_MARKETPLACE_ASSUMPTIONS!$B$10 | H18: =F18*G18 | I18: =(02_MARKETPLACE_ASSUMPTIONS!$B$4*02_MARKETPLACE_ASSUMPTIONS!$B$7+02_MARKETPLACE_ASSUMPTIONS!$B$5*02_MARKETPLACE_ASSUMPTIONS!$B$8+02_MARKETPLACE_ASSUMPTIONS!$B$6*02_MARKETPLACE_ASSUMPTIONS!$B$9) | J18: =H18*I18 | K18: Illustrative — validate in Alpha
A19: 16 | B19: =02_MARKETPLACE_ASSUMPTIONS!$B$12*(1+0.05)^15 | C19: =02_MARKETPLACE_ASSUMPTIONS!$B$11 | D19: =B19*C19 | E19: =02_MARKETPLACE_ASSUMPTIONS!$B$13 | F19: =D19*(1-E19) | G19: =02_MARKETPLACE_ASSUMPTIONS!$B$10 | H19: =F19*G19 | I19: =(02_MARKETPLACE_ASSUMPTIONS!$B$4*02_MARKETPLACE_ASSUMPTIONS!$B$7+02_MARKETPLACE_ASSUMPTIONS!$B$5*02_MARKETPLACE_ASSUMPTIONS!$B$8+02_MARKETPLACE_ASSUMPTIONS!$B$6*02_MARKETPLACE_ASSUMPTIONS!$B$9) | J19: =H19*I19 | K19: Illustrative — validate in Alpha
A20: 17 | B20: =02_MARKETPLACE_ASSUMPTIONS!$B$12*(1+0.05)^16 | C20: =02_MARKETPLACE_ASSUMPTIONS!$B$11 | D20: =B20*C20 | E20: =02_MARKETPLACE_ASSUMPTIONS!$B$13 | F20: =D20*(1-E20) | G20: =02_MARKETPLACE_ASSUMPTIONS!$B$10 | H20: =F20*G20 | I20: =(02_MARKETPLACE_ASSUMPTIONS!$B$4*02_MARKETPLACE_ASSUMPTIONS!$B$7+02_MARKETPLACE_ASSUMPTIONS!$B$5*02_MARKETPLACE_ASSUMPTIONS!$B$8+02_MARKETPLACE_ASSUMPTIONS!$B$6*02_MARKETPLACE_ASSUMPTIONS!$B$9) | J20: =H20*I20 | K20: Illustrative — validate in Alpha
A21: 18 | B21: =02_MARKETPLACE_ASSUMPTIONS!$B$12*(1+0.05)^17 | C21: =02_MARKETPLACE_ASSUMPTIONS!$B$11 | D21: =B21*C21 | E21: =02_MARKETPLACE_ASSUMPTIONS!$B$13 | F21: =D21*(1-E21) | G21: =02_MARKETPLACE_ASSUMPTIONS!$B$10 | H21: =F21*G21 | I21: =(02_MARKETPLACE_ASSUMPTIONS!$B$4*02_MARKETPLACE_ASSUMPTIONS!$B$7+02_MARKETPLACE_ASSUMPTIONS!$B$5*02_MARKETPLACE_ASSUMPTIONS!$B$8+02_MARKETPLACE_ASSUMPTIONS!$B$6*02_MARKETPLACE_ASSUMPTIONS!$B$9) | J21: =H21*I21 | K21: Illustrative — validate in Alpha
A22: 19 | B22: =02_MARKETPLACE_ASSUMPTIONS!$B$12*(1+0.05)^18 | C22: =02_MARKETPLACE_ASSUMPTIONS!$B$11 | D22: =B22*C22 | E22: =02_MARKETPLACE_ASSUMPTIONS!$B$13 | F22: =D22*(1-E22) | G22: =02_MARKETPLACE_ASSUMPTIONS!$B$10 | H22: =F22*G22 | I22: =(02_MARKETPLACE_ASSUMPTIONS!$B$4*02_MARKETPLACE_ASSUMPTIONS!$B$7+02_MARKETPLACE_ASSUMPTIONS!$B$5*02_MARKETPLACE_ASSUMPTIONS!$B$8+02_MARKETPLACE_ASSUMPTIONS!$B$6*02_MARKETPLACE_ASSUMPTIONS!$B$9) | J22: =H22*I22 | K22: Illustrative — validate in Alpha
A23: 20 | B23: =02_MARKETPLACE_ASSUMPTIONS!$B$12*(1+0.05)^19 | C23: =02_MARKETPLACE_ASSUMPTIONS!$B$11 | D23: =B23*C23 | E23: =02_MARKETPLACE_ASSUMPTIONS!$B$13 | F23: =D23*(1-E23) | G23: =02_MARKETPLACE_ASSUMPTIONS!$B$10 | H23: =F23*G23 | I23: =(02_MARKETPLACE_ASSUMPTIONS!$B$4*02_MARKETPLACE_ASSUMPTIONS!$B$7+02_MARKETPLACE_ASSUMPTIONS!$B$5*02_MARKETPLACE_ASSUMPTIONS!$B$8+02_MARKETPLACE_ASSUMPTIONS!$B$6*02_MARKETPLACE_ASSUMPTIONS!$B$9) | J23: =H23*I23 | K23: Illustrative — validate in Alpha
A24: 21 | B24: =02_MARKETPLACE_ASSUMPTIONS!$B$12*(1+0.05)^20 | C24: =02_MARKETPLACE_ASSUMPTIONS!$B$11 | D24: =B24*C24 | E24: =02_MARKETPLACE_ASSUMPTIONS!$B$13 | F24: =D24*(1-E24) | G24: =02_MARKETPLACE_ASSUMPTIONS!$B$10 | H24: =F24*G24 | I24: =(02_MARKETPLACE_ASSUMPTIONS!$B$4*02_MARKETPLACE_ASSUMPTIONS!$B$7+02_MARKETPLACE_ASSUMPTIONS!$B$5*02_MARKETPLACE_ASSUMPTIONS!$B$8+02_MARKETPLACE_ASSUMPTIONS!$B$6*02_MARKETPLACE_ASSUMPTIONS!$B$9) | J24: =H24*I24 | K24: Illustrative — validate in Alpha
A25: 22 | B25: =02_MARKETPLACE_ASSUMPTIONS!$B$12*(1+0.05)^21 | C25: =02_MARKETPLACE_ASSUMPTIONS!$B$11 | D25: =B25*C25 | E25: =02_MARKETPLACE_ASSUMPTIONS!$B$13 | F25: =D25*(1-E25) | G25: =02_MARKETPLACE_ASSUMPTIONS!$B$10 | H25: =F25*G25 | I25: =(02_MARKETPLACE_ASSUMPTIONS!$B$4*02_MARKETPLACE_ASSUMPTIONS!$B$7+02_MARKETPLACE_ASSUMPTIONS!$B$5*02_MARKETPLACE_ASSUMPTIONS!$B$8+02_MARKETPLACE_ASSUMPTIONS!$B$6*02_MARKETPLACE_ASSUMPTIONS!$B$9) | J25: =H25*I25 | K25: Illustrative — validate in Alpha
A26: 23 | B26: =02_MARKETPLACE_ASSUMPTIONS!$B$12*(1+0.05)^22 | C26: =02_MARKETPLACE_ASSUMPTIONS!$B$11 | D26: =B26*C26 | E26: =02_MARKETPLACE_ASSUMPTIONS!$B$13 | F26: =D26*(1-E26) | G26: =02_MARKETPLACE_ASSUMPTIONS!$B$10 | H26: =F26*G26 | I26: =(02_MARKETPLACE_ASSUMPTIONS!$B$4*02_MARKETPLACE_ASSUMPTIONS!$B$7+02_MARKETPLACE_ASSUMPTIONS!$B$5*02_MARKETPLACE_ASSUMPTIONS!$B$8+02_MARKETPLACE_ASSUMPTIONS!$B$6*02_MARKETPLACE_ASSUMPTIONS!$B$9) | J26: =H26*I26 | K26: Illustrative — validate in Alpha
A27: 24 | B27: =02_MARKETPLACE_ASSUMPTIONS!$B$12*(1+0.05)^23 | C27: =02_MARKETPLACE_ASSUMPTIONS!$B$11 | D27: =B27*C27 | E27: =02_MARKETPLACE_ASSUMPTIONS!$B$13 | F27: =D27*(1-E27) | G27: =02_MARKETPLACE_ASSUMPTIONS!$B$10 | H27: =F27*G27 | I27: =(02_MARKETPLACE_ASSUMPTIONS!$B$4*02_MARKETPLACE_ASSUMPTIONS!$B$7+02_MARKETPLACE_ASSUMPTIONS!$B$5*02_MARKETPLACE_ASSUMPTIONS!$B$8+02_MARKETPLACE_ASSUMPTIONS!$B$6*02_MARKETPLACE_ASSUMPTIONS!$B$9) | J27: =H27*I27 | K27: Illustrative — validate in Alpha

Sheet 05_BOOKING_MODEL
A1: Booking Model — Supply Capacity vs Demand
A3: Month | B3: Bookable listings | C3: Available nights | D3: Demand booked nights | E3: Capacity utilization | F3: Completed bookings | G3: Avg nights/booking | H3: GMV | I3: ADR | J3: Unserved demand | K3: Alpha target status | L3: Notes
A4: 1 | B4: =03_SUPPLY_MODEL!B4 | C4: =03_SUPPLY_MODEL!I4 | D4: =04_DEMAND_MODEL!H4 | E4: =IF(C4=0,0,D4/C4) | F4: =04_DEMAND_MODEL!F4 | G4: =04_DEMAND_MODEL!G4 | H4: =04_DEMAND_MODEL!J4 | I4: =04_DEMAND_MODEL!I4 | J4: =MAX(0,04_DEMAND_MODEL!D4-F4) | K4: =IF(SUM($F$4:F4)>=02_MARKETPLACE_ASSUMPTIONS!$B$21,"TARGET REACHED","IN PROGRESS") | L4: Capacity is a planning model; replace with actual availability after supply acquisition
A5: 2 | B5: =03_SUPPLY_MODEL!B5 | C5: =03_SUPPLY_MODEL!I5 | D5: =04_DEMAND_MODEL!H5 | E5: =IF(C5=0,0,D5/C5) | F5: =04_DEMAND_MODEL!F5 | G5: =04_DEMAND_MODEL!G5 | H5: =04_DEMAND_MODEL!J5 | I5: =04_DEMAND_MODEL!I5 | J5: =MAX(0,04_DEMAND_MODEL!D5-F5) | K5: =IF(SUM($F$4:F5)>=02_MARKETPLACE_ASSUMPTIONS!$B$21,"TARGET REACHED","IN PROGRESS") | L5: Capacity is a planning model; replace with actual availability after supply acquisition
A6: 3 | B6: =03_SUPPLY_MODEL!B6 | C6: =03_SUPPLY_MODEL!I6 | D6: =04_DEMAND_MODEL!H6 | E6: =IF(C6=0,0,D6/C6) | F6: =04_DEMAND_MODEL!F6 | G6: =04_DEMAND_MODEL!G6 | H6: =04_DEMAND_MODEL!J6 | I6: =04_DEMAND_MODEL!I6 | J6: =MAX(0,04_DEMAND_MODEL!D6-F6) | K6: =IF(SUM($F$4:F6)>=02_MARKETPLACE_ASSUMPTIONS!$B$21,"TARGET REACHED","IN PROGRESS") | L6: Capacity is a planning model; replace with actual availability after supply acquisition
A7: 4 | B7: =03_SUPPLY_MODEL!B7 | C7: =03_SUPPLY_MODEL!I7 | D7: =04_DEMAND_MODEL!H7 | E7: =IF(C7=0,0,D7/C7) | F7: =04_DEMAND_MODEL!F7 | G7: =04_DEMAND_MODEL!G7 | H7: =04_DEMAND_MODEL!J7 | I7: =04_DEMAND_MODEL!I7 | J7: =MAX(0,04_DEMAND_MODEL!D7-F7) | K7: =IF(SUM($F$4:F7)>=02_MARKETPLACE_ASSUMPTIONS!$B$21,"TARGET REACHED","IN PROGRESS") | L7: Capacity is a planning model; replace with actual availability after supply acquisition
A8: 5 | B8: =03_SUPPLY_MODEL!B8 | C8: =03_SUPPLY_MODEL!I8 | D8: =04_DEMAND_MODEL!H8 | E8: =IF(C8=0,0,D8/C8) | F8: =04_DEMAND_MODEL!F8 | G8: =04_DEMAND_MODEL!G8 | H8: =04_DEMAND_MODEL!J8 | I8: =04_DEMAND_MODEL!I8 | J8: =MAX(0,04_DEMAND_MODEL!D8-F8) | K8: =IF(SUM($F$4:F8)>=02_MARKETPLACE_ASSUMPTIONS!$B$21,"TARGET REACHED","IN PROGRESS") | L8: Capacity is a planning model; replace with actual availability after supply acquisition
A9: 6 | B9: =03_SUPPLY_MODEL!B9 | C9: =03_SUPPLY_MODEL!I9 | D9: =04_DEMAND_MODEL!H9 | E9: =IF(C9=0,0,D9/C9) | F9: =04_DEMAND_MODEL!F9 | G9: =04_DEMAND_MODEL!G9 | H9: =04_DEMAND_MODEL!J9 | I9: =04_DEMAND_MODEL!I9 | J9: =MAX(0,04_DEMAND_MODEL!D9-F9) | K9: =IF(SUM($F$4:F9)>=02_MARKETPLACE_ASSUMPTIONS!$B$21,"TARGET REACHED","IN PROGRESS") | L9: Capacity is a planning model; replace with actual availability after supply acquisition
A10: 7 | B10: =03_SUPPLY_MODEL!B10 | C10: =03_SUPPLY_MODEL!I10 | D10: =04_DEMAND_MODEL!H10 | E10: =IF(C10=0,0,D10/C10) | F10: =04_DEMAND_MODEL!F10 | G10: =04_DEMAND_MODEL!G10 | H10: =04_DEMAND_MODEL!J10 | I10: =04_DEMAND_MODEL!I10 | J10: =MAX(0,04_DEMAND_MODEL!D10-F10) | K10: =IF(SUM($F$4:F10)>=02_MARKETPLACE_ASSUMPTIONS!$B$21,"TARGET REACHED","IN PROGRESS") | L10: Capacity is a planning model; replace with actual availability after supply acquisition
A11: 8 | B11: =03_SUPPLY_MODEL!B11 | C11: =03_SUPPLY_MODEL!I11 | D11: =04_DEMAND_MODEL!H11 | E11: =IF(C11=0,0,D11/C11) | F11: =04_DEMAND_MODEL!F11 | G11: =04_DEMAND_MODEL!G11 | H11: =04_DEMAND_MODEL!J11 | I11: =04_DEMAND_MODEL!I11 | J11: =MAX(0,04_DEMAND_MODEL!D11-F11) | K11: =IF(SUM($F$4:F11)>=02_MARKETPLACE_ASSUMPTIONS!$B$21,"TARGET REACHED","IN PROGRESS") | L11: Capacity is a planning model; replace with actual availability after supply acquisition
A12: 9 | B12: =03_SUPPLY_MODEL!B12 | C12: =03_SUPPLY_MODEL!I12 | D12: =04_DEMAND_MODEL!H12 | E12: =IF(C12=0,0,D12/C12) | F12: =04_DEMAND_MODEL!F12 | G12: =04_DEMAND_MODEL!G12 | H12: =04_DEMAND_MODEL!J12 | I12: =04_DEMAND_MODEL!I12 | J12: =MAX(0,04_DEMAND_MODEL!D12-F12) | K12: =IF(SUM($F$4:F12)>=02_MARKETPLACE_ASSUMPTIONS!$B$21,"TARGET REACHED","IN PROGRESS") | L12: Capacity is a planning model; replace with actual availability after supply acquisition
A13: 10 | B13: =03_SUPPLY_MODEL!B13 | C13: =03_SUPPLY_MODEL!I13 | D13: =04_DEMAND_MODEL!H13 | E13: =IF(C13=0,0,D13/C13) | F13: =04_DEMAND_MODEL!F13 | G13: =04_DEMAND_MODEL!G13 | H13: =04_DEMAND_MODEL!J13 | I13: =04_DEMAND_MODEL!I13 | J13: =MAX(0,04_DEMAND_MODEL!D13-F13) | K13: =IF(SUM($F$4:F13)>=02_MARKETPLACE_ASSUMPTIONS!$B$21,"TARGET REACHED","IN PROGRESS") | L13: Capacity is a planning model; replace with actual availability after supply acquisition
A14: 11 | B14: =03_SUPPLY_MODEL!B14 | C14: =03_SUPPLY_MODEL!I14 | D14: =04_DEMAND_MODEL!H14 | E14: =IF(C14=0,0,D14/C14) | F14: =04_DEMAND_MODEL!F14 | G14: =04_DEMAND_MODEL!G14 | H14: =04_DEMAND_MODEL!J14 | I14: =04_DEMAND_MODEL!I14 | J14: =MAX(0,04_DEMAND_MODEL!D14-F14) | K14: =IF(SUM($F$4:F14)>=02_MARKETPLACE_ASSUMPTIONS!$B$21,"TARGET REACHED","IN PROGRESS") | L14: Capacity is a planning model; replace with actual availability after supply acquisition
A15: 12 | B15: =03_SUPPLY_MODEL!B15 | C15: =03_SUPPLY_MODEL!I15 | D15: =04_DEMAND_MODEL!H15 | E15: =IF(C15=0,0,D15/C15) | F15: =04_DEMAND_MODEL!F15 | G15: =04_DEMAND_MODEL!G15 | H15: =04_DEMAND_MODEL!J15 | I15: =04_DEMAND_MODEL!I15 | J15: =MAX(0,04_DEMAND_MODEL!D15-F15) | K15: =IF(SUM($F$4:F15)>=02_MARKETPLACE_ASSUMPTIONS!$B$21,"TARGET REACHED","IN PROGRESS") | L15: Capacity is a planning model; replace with actual availability after supply acquisition
... A27: 24 | B27: =03_SUPPLY_MODEL!B27 | C27: =03_SUPPLY_MODEL!I27 | D27: =04_DEMAND_MODEL!H27 | E27: =IF(C27=0,0,D27/C27) | F27: =04_DEMAND_MODEL!F27 | G27: =04_DEMAND_MODEL!G27 | H27: =04_DEMAND_MODEL!J27 | I27: =04_DEMAND_MODEL!I27 | J27: =MAX(0,04_DEMAND_MODEL!D27-F27) | K27: =IF(SUM($F$4:F27)>=02_MARKETPLACE_ASSUMPTIONS!$B$21,"TARGET REACHED","IN PROGRESS") | L27: Capacity is a planning model; replace with actual availability after supply acquisition

Sheet 06_REVENUE_MODEL
A1: Revenue Model — GMV → Platform Revenue
A3: Month | B3: GMV | C3: Alpha commission | D3: Base commission | E3: Upside commission | F3: Downside commission | G3: Alpha revenue | H3: Base revenue | I3: Upside revenue | J3: Downside revenue | K3: Payment cost | L3: Refund/service credits | M3: Net platform revenue (Base)
A4: 1 | B4: =05_BOOKING_MODEL!H4 | C4: =02_MARKETPLACE_ASSUMPTIONS!$B$16 | D4: =02_MARKETPLACE_ASSUMPTIONS!$B$17 | E4: =02_MARKETPLACE_ASSUMPTIONS!$B$18 | F4: =02_MARKETPLACE_ASSUMPTIONS!$B$19 | G4: =B4*C4 | H4: =B4*D4 | I4: =B4*E4 | J4: =B4*F4 | K4: =B4*02_MARKETPLACE_ASSUMPTIONS!$B$15 | L4: =B4*02_MARKETPLACE_ASSUMPTIONS!$B$14 | M4: =H4-K4-L4
A5: 2 | B5: =05_BOOKING_MODEL!H5 | C5: =02_MARKETPLACE_ASSUMPTIONS!$B$16 | D5: =02_MARKETPLACE_ASSUMPTIONS!$B$17 | E5: =02_MARKETPLACE_ASSUMPTIONS!$B$18 | F5: =02_MARKETPLACE_ASSUMPTIONS!$B$19 | G5: =B5*C5 | H5: =B5*D5 | I5: =B5*E5 | J5: =B5*F5 | K5: =B5*02_MARKETPLACE_ASSUMPTIONS!$B$15 | L5: =B5*02_MARKETPLACE_ASSUMPTIONS!$B$14 | M5: =H5-K5-L5
A6: 3 | B6: =05_BOOKING_MODEL!H6 | C6: =02_MARKETPLACE_ASSUMPTIONS!$B$16 | D6: =02_MARKETPLACE_ASSUMPTIONS!$B$17 | E6: =02_MARKETPLACE_ASSUMPTIONS!$B$18 | F6: =02_MARKETPLACE_ASSUMPTIONS!$B$19 | G6: =B6*C6 | H6: =B6*D6 | I6: =B6*E6 | J6: =B6*F6 | K6: =B6*02_MARKETPLACE_ASSUMPTIONS!$B$15 | L6: =B6*02_MARKETPLACE_ASSUMPTIONS!$B$14 | M6: =H6-K6-L6
A7: 4 | B7: =05_BOOKING_MODEL!H7 | C7: =02_MARKETPLACE_ASSUMPTIONS!$B$16 | D7: =02_MARKETPLACE_ASSUMPTIONS!$B$17 | E7: =02_MARKETPLACE_ASSUMPTIONS!$B$18 | F7: =02_MARKETPLACE_ASSUMPTIONS!$B$19 | G7: =B7*C7 | H7: =B7*D7 | I7: =B7*E7 | J7: =B7*F7 | K7: =B7*02_MARKETPLACE_ASSUMPTIONS!$B$15 | L7: =B7*02_MARKETPLACE_ASSUMPTIONS!$B$14 | M7: =H7-K7-L7
A8: 5 | B8: =05_BOOKING_MODEL!H8 | C8: =02_MARKETPLACE_ASSUMPTIONS!$B$16 | D8: =02_MARKETPLACE_ASSUMPTIONS!$B$17 | E8: =02_MARKETPLACE_ASSUMPTIONS!$B$18 | F8: =02_MARKETPLACE_ASSUMPTIONS!$B$19 | G8: =B8*C8 | H8: =B8*D8 | I8: =B8*E8 | J8: =B8*F8 | K8: =B8*02_MARKETPLACE_ASSUMPTIONS!$B$15 | L8: =B8*02_MARKETPLACE_ASSUMPTIONS!$B$14 | M8: =H8-K8-L8
A9: 6 | B9: =05_BOOKING_MODEL!H9 | C9: =02_MARKETPLACE_ASSUMPTIONS!$B$16 | D9: =02_MARKETPLACE_ASSUMPTIONS!$B$17 | E9: =02_MARKETPLACE_ASSUMPTIONS!$B$18 | F9: =02_MARKETPLACE_ASSUMPTIONS!$B$19 | G9: =B9*C9 | H9: =B9*D9 | I9: =B9*E9 | J9: =B9*F9 | K9: =B9*02_MARKETPLACE_ASSUMPTIONS!$B$15 | L9: =B9*02_MARKETPLACE_ASSUMPTIONS!$B$14 | M9: =H9-K9-L9
A10: 7 | B10: =05_BOOKING_MODEL!H10 | C10: =02_MARKETPLACE_ASSUMPTIONS!$B$16 | D10: =02_MARKETPLACE_ASSUMPTIONS!$B$17 | E10: =02_MARKETPLACE_ASSUMPTIONS!$B$18 | F10: =02_MARKETPLACE_ASSUMPTIONS!$B$19 | G10: =B10*C10 | H10: =B10*D10 | I10: =B10*E10 | J10: =B10*F10 | K10: =B10*02_MARKETPLACE_ASSUMPTIONS!$B$15 | L10: =B10*02_MARKETPLACE_ASSUMPTIONS!$B$14 | M10: =H10-K10-L10
A11: 8 | B11: =05_BOOKING_MODEL!H11 | C11: =02_MARKETPLACE_ASSUMPTIONS!$B$16 | D11: =02_MARKETPLACE_ASSUMPTIONS!$B$17 | E11: =02_MARKETPLACE_ASSUMPTIONS!$B$18 | F11: =02_MARKETPLACE_ASSUMPTIONS!$B$19 | G11: =B11*C11 | H11: =B11*D11 | I11: =B11*E11 | J11: =B11*F11 | K11: =B11*02_MARKETPLACE_ASSUMPTIONS!$B$15 | L11: =B11*02_MARKETPLACE_ASSUMPTIONS!$B$14 | M11: =H11-K11-L11
A12: 9 | B12: =05_BOOKING_MODEL!H12 | C12: =02_MARKETPLACE_ASSUMPTIONS!$B$16 | D12: =02_MARKETPLACE_ASSUMPTIONS!$B$17 | E12: =02_MARKETPLACE_ASSUMPTIONS!$B$18 | F12: =02_MARKETPLACE_ASSUMPTIONS!$B$19 | G12: =B12*C12 | H12: =B12*D12 | I12: =B12*E12 | J12: =B12*F12 | K12: =B12*02_MARKETPLACE_ASSUMPTIONS!$B$15 | L12: =B12*02_MARKETPLACE_ASSUMPTIONS!$B$14 | M12: =H12-K12-L12
A13: 10 | B13: =05_BOOKING_MODEL!H13 | C13: =02_MARKETPLACE_ASSUMPTIONS!$B$16 | D13: =02_MARKETPLACE_ASSUMPTIONS!$B$17 | E13: =02_MARKETPLACE_ASSUMPTIONS!$B$18 | F13: =02_MARKETPLACE_ASSUMPTIONS!$B$19 | G13: =B13*C13 | H13: =B13*D13 | I13: =B13*E13 | J13: =B13*F13 | K13: =B13*02_MARKETPLACE_ASSUMPTIONS!$B$15 | L13: =B13*02_MARKETPLACE_ASSUMPTIONS!$B$14 | M13: =H13-K13-L13
A14: 11 | B14: =05_BOOKING_MODEL!H14 | C14: =02_MARKETPLACE_ASSUMPTIONS!$B$16 | D14: =02_MARKETPLACE_ASSUMPTIONS!$B$17 | E14: =02_MARKETPLACE_ASSUMPTIONS!$B$18 | F14: =02_MARKETPLACE_ASSUMPTIONS!$B$19 | G14: =B14*C14 | H14: =B14*D14 | I14: =B14*E14 | J14: =B14*F14 | K14: =B14*02_MARKETPLACE_ASSUMPTIONS!$B$15 | L14: =B14*02_MARKETPLACE_ASSUMPTIONS!$B$14 | M14: =H14-K14-L14
A15: 12 | B15: =05_BOOKING_MODEL!H15 | C15: =02_MARKETPLACE_ASSUMPTIONS!$B$16 | D15: =02_MARKETPLACE_ASSUMPTIONS!$B$17 | E15: =02_MARKETPLACE_ASSUMPTIONS!$B$18 | F15: =02_MARKETPLACE_ASSUMPTIONS!$B$19 | G15: =B15*C15 | H15: =B15*D15 | I15: =B15*E15 | J15: =B15*F15 | K15: =B15*02_MARKETPLACE_ASSUMPTIONS!$B$15 | L15: =B15*02_MARKETPLACE_ASSUMPTIONS!$B$14 | M15: =H15-K15-L15
... A27: 24 | B27: =05_BOOKING_MODEL!H27 | C27: =02_MARKETPLACE_ASSUMPTIONS!$B$16 | D27: =02_MARKETPLACE_ASSUMPTIONS!$B$17 | E27: =02_MARKETPLACE_ASSUMPTIONS!$B$18 | F27: =02_MARKETPLACE_ASSUMPTIONS!$B$19 | G27: =B27*C27 | H27: =B27*D27 | I27: =B27*E27 | J27: =B27*F27 | K27: =B27*02_MARKETPLACE_ASSUMPTIONS!$B$15 | L27: =B27*02_MARKETPLACE_ASSUMPTIONS!$B$14 | M27: =H27-K27-L27

Sheet 07_VARIABLE_COSTS
A1: Variable Costs
A3: Month | B3: GMV | C3: Payment processing | D3: Refund/service credits | E3: Host incentives | F3: Other variable costs | G3: Total variable costs | H3: Variable cost % GMV | I3: Notes
A4: 1 | B4: =06_REVENUE_MODEL!B4 | C4: =06_REVENUE_MODEL!K4 | D4: =06_REVENUE_MODEL!L4 | E4: 0 | F4: 0 | G4: =SUM(C4:F4) | H4: =IF(B4=0,0,G4/B4) | I4: Host incentives intentionally separated from commission assumption
A5: 2 | B5: =06_REVENUE_MODEL!B5 | C5: =06_REVENUE_MODEL!K5 | D5: =06_REVENUE_MODEL!L5 | E5: 0 | F5: 0 | G5: =SUM(C5:F5) | H5: =IF(B5=0,0,G5/B5) | I5: Host incentives intentionally separated from commission assumption
A6: 3 | B6: =06_REVENUE_MODEL!B6 | C6: =06_REVENUE_MODEL!K6 | D6: =06_REVENUE_MODEL!L6 | E6: 0 | F6: 0 | G6: =SUM(C6:F6) | H6: =IF(B6=0,0,G6/B6) | I6: Host incentives intentionally separated from commission assumption
A7: 4 | B7: =06_REVENUE_MODEL!B7 | C7: =06_REVENUE_MODEL!K7 | D7: =06_REVENUE_MODEL!L7 | E7: 0 | F7: 0 | G7: =SUM(C7:F7) | H7: =IF(B7=0,0,G7/B7) | I7: Host incentives intentionally separated from commission assumption
A8: 5 | B8: =06_REVENUE_MODEL!B8 | C8: =06_REVENUE_MODEL!K8 | D8: =06_REVENUE_MODEL!L8 | E8: 0 | F8: 0 | G8: =SUM(C8:F8) | H8: =IF(B8=0,0,G8/B8) | I8: Host incentives intentionally separated from commission assumption
A9: 6 | B9: =06_REVENUE_MODEL!B9 | C9: =06_REVENUE_MODEL!K9 | D9: =06_REVENUE_MODEL!L9 | E9: 0 | F9: 0 | G9: =SUM(C9:F9) | H9: =IF(B9=0,0,G9/B9) | I9: Host incentives intentionally separated from commission assumption
A10: 7 | B10: =06_REVENUE_MODEL!B10 | C10: =06_REVENUE_MODEL!K10 | D10: =06_REVENUE_MODEL!L10 | E10: 0 | F10: 0 | G10: =SUM(C10:F10) | H10: =IF(B10=0,0,G10/B10) | I10: Host incentives intentionally separated from commission assumption
A11: 8 | B11: =06_REVENUE_MODEL!B11 | C11: =06_REVENUE_MODEL!K11 | D11: =06_REVENUE_MODEL!L11 | E11: 0 | F11: 0 | G11: =SUM(C11:F11) | H11: =IF(B11=0,0,G11/B11) | I11: Host incentives intentionally separated from commission assumption
A12: 9 | B12: =06_REVENUE_MODEL!B12 | C12: =06_REVENUE_MODEL!K12 | D12: =06_REVENUE_MODEL!L12 | E12: 0 | F12: 0 | G12: =SUM(C12:F12) | H12: =IF(B12=0,0,G12/B12) | I12: Host incentives intentionally separated from commission assumption
A13: 10 | B13: =06_REVENUE_MODEL!B13 | C13: =06_REVENUE_MODEL!K13 | D13: =06_REVENUE_MODEL!L13 | E13: 0 | F13: 0 | G13: =SUM(C13:F13) | H13: =IF(B13=0,0,G13/B13) | I13: Host incentives intentionally separated from commission assumption
A14: 11 | B14: =06_REVENUE_MODEL!B14 | C14: =06_REVENUE_MODEL!K14 | D14: =06_REVENUE_MODEL!L14 | E14: 0 | F14: 0 | G14: =SUM(C14:F14) | H14: =IF(B14=0,0,G14/B14) | I14: Host incentives intentionally separated from commission assumption
A15: 12 | B15: =06_REVENUE_MODEL!B15 | C15: =06_REVENUE_MODEL!K15 | D15: =06_REVENUE_MODEL!L15 | E15: 0 | F15: 0 | G15: =SUM(C15:F15) | H15: =IF(B15=0,0,G15/B15) | I15: Host incentives intentionally separated from commission assumption
... A27: 24 | B27: =06_REVENUE_MODEL!B27 | C27: =06_REVENUE_MODEL!K27 | D27: =06_REVENUE_MODEL!L27 | E27: 0 | F27: 0 | G27: =SUM(C27:F27) | H27: =IF(B27=0,0,G27/B27) | I27: Host incentives intentionally separated from commission assumption

Sheet 08_FIXED_COSTS
A1: Fixed Operating Costs
A3: Month | B3: Payroll | C3: Infrastructure | D3: Office/Admin | E3: Marketing | F3: Legal/Compliance | G3: Other fixed | H3: Total fixed costs | I3: Notes
A4: 1 | B4: =02_MARKETPLACE_ASSUMPTIONS!$B$20 | C4: =02_MARKETPLACE_ASSUMPTIONS!$B$21 | D4: =02_MARKETPLACE_ASSUMPTIONS!$B$22 | E4: =02_MARKETPLACE_ASSUMPTIONS!$B$23 | F4: 0 | G4: 0 | H4: =SUM(B4:G4) | I4: Planning assumptions — replace with actual commitments
A5: 2 | B5: =02_MARKETPLACE_ASSUMPTIONS!$B$20 | C5: =02_MARKETPLACE_ASSUMPTIONS!$B$21 | D5: =02_MARKETPLACE_ASSUMPTIONS!$B$22 | E5: =02_MARKETPLACE_ASSUMPTIONS!$B$23 | F5: 0 | G5: 0 | H5: =SUM(B5:G5) | I5: Planning assumptions — replace with actual commitments
A6: 3 | B6: =02_MARKETPLACE_ASSUMPTIONS!$B$20 | C6: =02_MARKETPLACE_ASSUMPTIONS!$B$21 | D6: =02_MARKETPLACE_ASSUMPTIONS!$B$22 | E6: =02_MARKETPLACE_ASSUMPTIONS!$B$23 | F6: 0 | G6: 0 | H6: =SUM(B6:G6) | I6: Planning assumptions — replace with actual commitments
A7: 4 | B7: =02_MARKETPLACE_ASSUMPTIONS!$B$20 | C7: =02_MARKETPLACE_ASSUMPTIONS!$B$21 | D7: =02_MARKETPLACE_ASSUMPTIONS!$B$22 | E7: =02_MARKETPLACE_ASSUMPTIONS!$B$23 | F7: 0 | G7: 0 | H7: =SUM(B7:G7) | I7: Planning assumptions — replace with actual commitments
A8: 5 | B8: =02_MARKETPLACE_ASSUMPTIONS!$B$20 | C8: =02_MARKETPLACE_ASSUMPTIONS!$B$21 | D8: =02_MARKETPLACE_ASSUMPTIONS!$B$22 | E8: =02_MARKETPLACE_ASSUMPTIONS!$B$23 | F8: 0 | G8: 0 | H8: =SUM(B8:G8) | I8: Planning assumptions — replace with actual commitments
A9: 6 | B9: =02_MARKETPLACE_ASSUMPTIONS!$B$20 | C9: =02_MARKETPLACE_ASSUMPTIONS!$B$21 | D9: =02_MARKETPLACE_ASSUMPTIONS!$B$22 | E9: =02_MARKETPLACE_ASSUMPTIONS!$B$23 | F9: 0 | G9: 0 | H9: =SUM(B9:G9) | I9: Planning assumptions — replace with actual commitments
A10: 7 | B10: =02_MARKETPLACE_ASSUMPTIONS!$B$20 | C10: =02_MARKETPLACE_ASSUMPTIONS!$B$21 | D10: =02_MARKETPLACE_ASSUMPTIONS!$B$22 | E10: =02_MARKETPLACE_ASSUMPTIONS!$B$23 | F10: 0 | G10: 0 | H10: =SUM(B10:G10) | I10: Planning assumptions — replace with actual commitments
A11: 8 | B11: =02_MARKETPLACE_ASSUMPTIONS!$B$20 | C11: =02_MARKETPLACE_ASSUMPTIONS!$B$21 | D11: =02_MARKETPLACE_ASSUMPTIONS!$B$22 | E11: =02_MARKETPLACE_ASSUMPTIONS!$B$23 | F11: 0 | G11: 0 | H11: =SUM(B11:G11) | I11: Planning assumptions — replace with actual commitments
A12: 9 | B12: =02_MARKETPLACE_ASSUMPTIONS!$B$20 | C12: =02_MARKETPLACE_ASSUMPTIONS!$B$21 | D12: =02_MARKETPLACE_ASSUMPTIONS!$B$22 | E12: =02_MARKETPLACE_ASSUMPTIONS!$B$23 | F12: 0 | G12: 0 | H12: =SUM(B12:G12) | I12: Planning assumptions — replace with actual commitments
A13: 10 | B13: =02_MARKETPLACE_ASSUMPTIONS!$B$20 | C13: =02_MARKETPLACE_ASSUMPTIONS!$B$21 | D13: =02_MARKETPLACE_ASSUMPTIONS!$B$22 | E13: =02_MARKETPLACE_ASSUMPTIONS!$B$23 | F13: 0 | G13: 0 | H13: =SUM(B13:G13) | I13: Planning assumptions — replace with actual commitments
A14: 11 | B14: =02_MARKETPLACE_ASSUMPTIONS!$B$20 | C14: =02_MARKETPLACE_ASSUMPTIONS!$B$21 | D14: =02_MARKETPLACE_ASSUMPTIONS!$B$22 | E14: =02_MARKETPLACE_ASSUMPTIONS!$B$23 | F14: 0 | G14: 0 | H14: =SUM(B14:G14) | I14: Planning assumptions — replace with actual commitments
A15: 12 | B15: =02_MARKETPLACE_ASSUMPTIONS!$B$20 | C15: =02_MARKETPLACE_ASSUMPTIONS!$B$21 | D15: =02_MARKETPLACE_ASSUMPTIONS!$B$22 | E15: =02_MARKETPLACE_ASSUMPTIONS!$B$23 | F15: 0 | G15: 0 | H15: =SUM(B15:G15) | I15: Planning assumptions — replace with actual commitments
... A27: 24 | B27: =02_MARKETPLACE_ASSUMPTIONS!$B$20 | C27: =02_MARKETPLACE_ASSUMPTIONS!$B$21 | D27: =02_MARKETPLACE_ASSUMPTIONS!$B$22 | E27: =02_MARKETPLACE_ASSUMPTIONS!$B$23 | F27: 0 | G27: 0 | H27: =SUM(B27:G27) | I27: Planning assumptions — replace with actual commitments

Sheet 09_HEADCOUNT
A1: Headcount & Payroll Logic
A3: Role | B3: Current planned monthly cost | C3: Trigger / rationale | D3: Status | E3: Year 1 notes | F3: Year 2 notes
A4: Office Manager | B4: 15000 | C4: Core operations | D4: Draft assumption | E4: Keep only if workload justifies | F4: Review after alpha
A5: Accounting | B5: 4000 | C5: Transaction/admin complexity | D5: Draft assumption | E5: May be outsourced | F5: Review
A6: Operations/Host | B6: 10000 | C6: Supply onboarding + support | D6: Draft assumption | E6: Critical when real listings acquired | F6: Scale with listings
A7: Customer Service | B7: 0 | C7: Add when support volume warrants | D7: Deferred | E7: Not required at zero real users | F7: Trigger by demand

Sheet 10_P&L
A1: 24-Month P&L — Base Case
A3: Month | B3: Net platform revenue | C3: Variable costs | D3: Contribution profit | E3: Fixed costs | F3: EBITDA before tax | G3: Cumulative EBITDA | H3: Comment
A4: 1 | B4: =06_REVENUE_MODEL!M4 | C4: =07_VARIABLE_COSTS!G4 | D4: =B4-C4 | E4: =08_FIXED_COSTS!H4 | F4: =D4-E4 | G4: =SUM($F$4:F4) | H4: =IF(F4>0,"Positive","Burn")
A5: 2 | B5: =06_REVENUE_MODEL!M5 | C5: =07_VARIABLE_COSTS!G5 | D5: =B5-C5 | E5: =08_FIXED_COSTS!H5 | F5: =D5-E5 | G5: =SUM($F$4:F5) | H5: =IF(F5>0,"Positive","Burn")
A6: 3 | B6: =06_REVENUE_MODEL!M6 | C6: =07_VARIABLE_COSTS!G6 | D6: =B6-C6 | E6: =08_FIXED_COSTS!H6 | F6: =D6-E6 | G6: =SUM($F$4:F6) | H6: =IF(F6>0,"Positive","Burn")
A7: 4 | B7: =06_REVENUE_MODEL!M7 | C7: =07_VARIABLE_COSTS!G7 | D7: =B7-C7 | E7: =08_FIXED_COSTS!H7 | F7: =D7-E7 | G7: =SUM($F$4:F7) | H7: =IF(F7>0,"Positive","Burn")
A8: 5 | B8: =06_REVENUE_MODEL!M8 | C8: =07_VARIABLE_COSTS!G8 | D8: =B8-C8 | E8: =08_FIXED_COSTS!H8 | F8: =D8-E8 | G8: =SUM($F$4:F8) | H8: =IF(F8>0,"Positive","Burn")
A9: 6 | B9: =06_REVENUE_MODEL!M9 | C9: =07_VARIABLE_COSTS!G9 | D9: =B9-C9 | E9: =08_FIXED_COSTS!H9 | F9: =D9-E9 | G9: =SUM($F$4:F9) | H9: =IF(F9>0,"Positive","Burn")
A10: 7 | B10: =06_REVENUE_MODEL!M10 | C10: =07_VARIABLE_COSTS!G10 | D10: =B10-C10 | E10: =08_FIXED_COSTS!H10 | F10: =D10-E10 | G10: =SUM($F$4:F10) | H10: =IF(F10>0,"Positive","Burn")
A11: 8 | B11: =06_REVENUE_MODEL!M11 | C11: =07_VARIABLE_COSTS!G11 | D11: =B11-C11 | E11: =08_FIXED_COSTS!H11 | F11: =D11-E11 | G11: =SUM($F$4:F11) | H11: =IF(F11>0,"Positive","Burn")
A12: 9 | B12: =06_REVENUE_MODEL!M12 | C12: =07_VARIABLE_COSTS!G12 | D12: =B12-C12 | E12: =08_FIXED_COSTS!H12 | F12: =D12-E12 | G12: =SUM($F$4:F12) | H12: =IF(F12>0,"Positive","Burn")
A13: 10 | B13: =06_REVENUE_MODEL!M13 | C13: =07_VARIABLE_COSTS!G13 | D13: =B13-C13 | E13: =08_FIXED_COSTS!H13 | F13: =D13-E13 | G13: =SUM($F$4:F13) | H13: =IF(F13>0,"Positive","Burn")
A14: 11 | B14: =06_REVENUE_MODEL!M14 | C14: =07_VARIABLE_COSTS!G14 | D14: =B14-C14 | E14: =08_FIXED_COSTS!H14 | F14: =D14-E14 | G14: =SUM($F$4:F14) | H14: =IF(F14>0,"Positive","Burn")
A15: 12 | B15: =06_REVENUE_MODEL!M15 | C15: =07_VARIABLE_COSTS!G15 | D15: =B15-C15 | E15: =08_FIXED_COSTS!H15 | F15: =D15-E15 | G15: =SUM($F$4:F15) | H15: =IF(F15>0,"Positive","Burn")
... A27: 24 | B27: =06_REVENUE_MODEL!M27 | C27: =07_VARIABLE_COSTS!G27 | D27: =B27-C27 | E27: =08_FIXED_COSTS!H27 | F27: =D27-E27 | G27: =SUM($F$4:F27) | H27: =IF(F27>0,"Positive","Burn")

Sheet 11_CASH_FLOW
A1: Cash Flow & Runway
A3: Month | B3: Opening cash | C3: Operating cash flow | D3: Capex / setup | E3: Net cash flow | F3: Closing cash | G3: Cash burn | H3: Runway status
A4: 1 | B4: 0 | C4: =10_P&L!F4 | D4: 40000 | E4: =C4-D4 | F4: =B4+E4 | G4: =MAX(0,-E4) | H4: =IF(F4<=0,"Funding required","Positive")
A5: 2 | B5: =F4 | C5: =10_P&L!F5 | D5: 0 | E5: =C5-D5 | F5: =B5+E5 | G5: =MAX(0,-E5) | H5: =IF(F5<=0,"Funding required","Positive")
A6: 3 | B6: =F5 | C6: =10_P&L!F6 | D6: 0 | E6: =C6-D6 | F6: =B6+E6 | G6: =MAX(0,-E6) | H6: =IF(F6<=0,"Funding required","Positive")
A7: 4 | B7: =F6 | C7: =10_P&L!F7 | D7: 0 | E7: =C7-D7 | F7: =B7+E7 | G7: =MAX(0,-E7) | H7: =IF(F7<=0,"Funding required","Positive")
A8: 5 | B8: =F7 | C8: =10_P&L!F8 | D8: 0 | E8: =C8-D8 | F8: =B8+E8 | G8: =MAX(0,-E8) | H8: =IF(F8<=0,"Funding required","Positive")
A9: 6 | B9: =F8 | C9: =10_P&L!F9 | D9: 0 | E9: =C9-D9 | F9: =B9+E9 | G9: =MAX(0,-E9) | H9: =IF(F9<=0,"Funding required","Positive")
A10: 7 | B10: =F9 | C10: =10_P&L!F10 | D10: 0 | E10: =C10-D10 | F10: =B10+E10 | G10: =MAX(0,-E10) | H10: =IF(F10<=0,"Funding required","Positive")
A11: 8 | B11: =F10 | C11: =10_P&L!F11 | D11: 0 | E11: =C11-D11 | F11: =B11+E11 | G11: =MAX(0,-E11) | H11: =IF(F11<=0,"Funding required","Positive")
A12: 9 | B12: =F11 | C12: =10_P&L!F12 | D12: 0 | E12: =C12-D12 | F12: =B12+E12 | G12: =MAX(0,-E12) | H12: =IF(F12<=0,"Funding required","Positive")
A13: 10 | B13: =F12 | C13: =10_P&L!F13 | D13: 0 | E13: =C13-D13 | F13: =B13+E13 | G13: =MAX(0,-E13) | H13: =IF(F13<=0,"Funding required","Positive")
A14: 11 | B14: =F13 | C14: =10_P&L!F14 | D14: 0 | E14: =C14-D14 | F14: =B14+E14 | G14: =MAX(0,-E14) | H14: =IF(F14<=0,"Funding required","Positive")
A15: 12 | B15: =F14 | C15: =10_P&L!F15 | D15: 0 | E15: =C15-D15 | F15: =B15+E15 | G15: =MAX(0,-E15) | H15: =IF(F15<=0,"Funding required","Positive")
A16: 13 | B16: =F15 | C16: =10_P&L!F16 | D16: 0 | E16: =C16-D16 | F16: =B16+E16 | G16: =MAX(0,-E16) | H16: =IF(F16<=0,"Funding required","Positive")
... A27: 24 | B27: =F26 | C27: =10_P&L!F27 | D27: 0 | E27: =C27-D27 | F27: =B27+E27 | G27: =MAX(0,-E27) | H27: =IF(F27<=0,"Funding required","Positive")

Sheet 12_UNIT_ECONOMICS
A1: Unit Economics — Explicitly Unvalidated Until Alpha
A3: Metric | B3: Formula / value | C3: Unit | D3: Status | E3: Interpretation
A4: Average ADR | B4: =04_DEMAND_MODEL!I4 | C4: EGP/night | D4: Derived | E4: Depends on listing mix and assumed ADRs
A5: Average nights / booking | B5: =02_MARKETPLACE_ASSUMPTIONS!B10 | C5: nights | D5: Draft assumption | E5: Must be measured
A6: Revenue / booking (Base) | B6: =B4*B5*02_MARKETPLACE_ASSUMPTIONS!B17 | C6: EGP | D6: Derived | E6: Post-alpha base commission only
A7: Payment cost / booking | B7: =B6*02_MARKETPLACE_ASSUMPTIONS!B15 | C7: EGP | D7: Derived | E7: Processor-dependent
A8: Contribution / booking | B8: =B6-B7 | C8: EGP | D8: Derived | E8: Before fixed costs
A9: CAC | B9: =0 | C9: EGP/customer | D9: Not available | E9: No real acquisition evidence yet
A10: LTV | B10: =0 | C10: EGP/customer | D10: Not available | E10: No retention/transaction history
A11: LTV:CAC | B11: =0 | C11: ratio | D11: Not available | E11: Do not use for investment decisions yet

Sheet 13_SCENARIOS
A1: Scenario Comparison — Downside / Base / Upside
A3: Driver | B3: Downside | C3: Base | D3: Upside | E3: Status | F3: Source / rationale
A4: Post-alpha commission | B4: 0.08 | C4: 0.1 | D4: 0.12 | E4: Scenario | F4: Founder workbook range adapted as scenarios
A5: Monthly qualified demand | B5: 60 | C5: 100 | D5: 160 | E5: Draft assumption | F5: Must be validated
A6: Booking conversion | B6: 0.015 | C6: 0.03 | D6: 0.05 | E6: Draft assumption | F6: Must be validated
A7: Average nights / booking | B7: 2 | C7: 2.5 | D7: 3 | E7: Draft assumption | F7: Must be validated
A8: Monthly marketing | B8: 5000 | C8: 10000 | D8: 20000 | E8: Draft assumption | F8: Must be validated
A9: Monthly payroll | B9: 25000 | C9: 29000 | D9: 40000 | E9: Draft assumption | F9: Must be validated

Sheet 14_ALPHA_MODEL
A1: Closed Alpha Model — Validation First
A3: Metric | B3: Current evidence | C3: Alpha target / rule | D3: Status | E3: Why it matters | F3: Owner action
A4: Real users | B4: 0 | C4: Acquire first users | D4: Not started | E4: Demand validation | F4: Founder
A5: Real bookable listings | B5: 0 | C5: Acquire 3–5 real listings | D5: Not started | E5: Supply validation | F5: Founder
A6: Bookings | B6: 0 | C6: 7 by Week 6 (10 only if supply condition met) | D6: Not started | E6: Core transaction proof | F6: Founder + team
A7: Revenue | B7: 0 | C7: 0% platform commission during alpha | D7: Current rule | E7: Validate behavior before monetization | F7: Founder
A8: Differentiation evidence | B8: 0 | C8: Guest feedback + repeat/choice evidence | D8: Not started | E8: Core hypothesis | F8: Founder
A9: Booking CTA on OPPO | B9: 0 | C9: Must work before booking loop | D9: P0 blocker | E9: Technical gate | F9: Engineering

Sheet 15_KPI_DASHBOARD
A1: StayOS Financial & Marketplace Dashboard
A3: Current real listings | B3: 0 | C3: Current evidence
A4: Current real bookings | B4: 0 | C4: Current evidence
A5: Current real users | B5: 0 | C5: Current evidence
A6: Alpha booking target | B6: 7 | C6: Current decision
A7: Modeled 24M GMV | B7: =SUM('06_REVENUE_MODEL'!B4:B27) | C7: Illustrative model
A8: Modeled 24M Base revenue | B8: =SUM('06_REVENUE_MODEL'!H4:H27) | C8: Illustrative model
A9: Modeled 24M Base net platform revenue | B9: =SUM('06_REVENUE_MODEL'!M4:M27) | C9: Illustrative model
A10: Modeled 24M EBITDA | B10: =SUM('10_P&L'!F4:F27) | C10: Illustrative model
A11: Break-even month | B11: =IFERROR(MATCH(TRUE,INDEX('10_P&L'!G4:G27>=0,0),0),"Not reached") | C11: Illustrative model
